Workbook
Name Age: '[1]Calc Engine'!$C$31:$C$89
Name Age: '[2]Calc Engine'!$C$31:$C$89
Name Age: '[2]Calc Engine'!$C$31:$C$89
Name Age: 'Calc Engine'!$C$31:$C$89
Name Allocation_Large_Cap: 'Calc Engine'!$AM$21
Name Allocation_Mid_Cap: 'Calc Engine'!$AM$22
Name Allocation_Small_Cap: 'Calc Engine'!$AM$23
Name End_Of_Year_Value_Large_Cap: '[1]Calc Engine'!$AO$31:$AO$89
Name End_Of_Year_Value_Large_Cap: '[2]Calc Engine'!$AO$31:$AO$89
Name End_Of_Year_Value_Large_Cap: '[2]Calc Engine'!$AO$31:$AO$89
Name End_Of_Year_Value_Large_Cap: 'Calc Engine'!$AO$31:$AO$89
Name End_Of_Year_Value_Mid_Cap: '[1]Calc Engine'!$AT$31:$AT$89
Name End_Of_Year_Value_Mid_Cap: '[2]Calc Engine'!$AT$31:$AT$89
Name End_Of_Year_Value_Mid_Cap: '[2]Calc Engine'!$AT$31:$AT$89
Name End_Of_Year_Value_Mid_Cap: 'Calc Engine'!$AT$31:$AT$89
Name End_Of_Year_Value_Small_Cap: '[1]Calc Engine'!$AY$31:$AY$89
Name End_Of_Year_Value_Small_Cap: '[2]Calc Engine'!$AY$31:$AY$89
Name End_Of_Year_Value_Small_Cap: '[2]Calc Engine'!$AY$31:$AY$89
Name End_Of_Year_Value_Small_Cap: 'Calc Engine'!$AY$31:$AY$89
Name Opening_Savings: Details!$V$20
Name Opening_Savings: [2]Details!$V$20
Name Opening_Savings: [1]Details!$V$20
Name Total_Surplus: '[1]Calc Engine'!$BH$5
Name Total_Surplus: '[2]Calc Engine'!$BH$5
Name Total_Surplus: '[2]Calc Engine'!$BH$5
Name Total_Surplus: 'Calc Engine'!$BH$5

Sheet Details
B2: Name | C2: Gaurav Agarwal
B3: Start Age | C3: 20
B4: Goal Age | C4: 55
S6: Portfolio Structure
B7: Income | F7: Expenses | J7: Goal | U7: 1 | V7: 2 | W7: 3 | X7: 4 | Y7: 5 | Z7: 6 | AB7: Scenario Structure
B8: Annual | C8: =SUM(Details!$C$14:$C$18) -> 726000 | D8: =SUM(Details!$D$14:$D$18) -> 1 | F8: Annual | G8: =SUM(Details!$G$14:$G$22) -> 210000 | H8: =IFERROR($G8/$C$8,"-") -> 0.2892562 | U8: Share (%) | V8: Share (%) | W8: Share (%) | X8: Share (%) | Y8: Share (%) | Z8: Share (%) | AC8: Best | AD8: Medium | AE8: Worst
F9: Balance | G9: =(C8-G8) -> 516000 | H9: =1-H8 -> 0.7107438 | K9: 1 - least imp | S9: Large Cap | U9: 0.2 | V9: 0 | W9: 0.2 | X9: 0.9 | Y9: 0.1 | Z9: 0.8 | AB9: Good | AC9: 0.8 | AD9: 0.2 | AE9: 0
F10: Minimum amount to invest | G10: 40000 | H10: =IF(G10>G9,"Insufficent","-") -> - | K10: 3 - most imp | S10: Mid Cap | U10: 0.5 | V10: 0.5 | W10: 0.7 | X10: 0.05 | Y10: 0.05 | Z10: 0.1 | AB10: Mid | AC10: 0.1 | AD10: 0.5 | AE10: 0.2
F11: Yearly Increment in Investment Amount | H11: 0.1 | L11: In Rs - Goal Value | S11: Small Cap | U11: 0.3 | V11: 0.5 | W11: 0.1 | X11: 0.05 | Y11: 0.9 | Z11: 0.1 | AB11: Worst | AC11: 0.1 | AD11: 0.3 | AE11: 0.8
L12: Source | S12: % of Goals Met | U12: ='[2]Calc Engine'!$BF3 -> #REF! | V12: =#REF! -> #REF! | W12: =#REF! -> #REF! | X12: =#REF! -> #REF! | Y12: =#REF! -> #REF! | Z12: =#REF! -> #REF! | AC12: =IF(SUM(AC9:AC11) = 1, "", "Sum != 1") | AD12: =IF(SUM(AD9:AD11) = 1, "", "Sum != 1") | AE12: =IF(SUM(AE9:AE11) = 1, "", "Sum != 1")
B13: Category | C13: in Rs | D13: in % | F13: Category | G13: in Rs | H13: in % | J13: Goal | K13: Goal Importance | L13: At Age | M13: Large Cap | N13: Mid Cap | O13: Small Cap | AB13: Select The Sceanario | AE13: Best
B14: Salary | C14: 720000 | D14: =IFERROR($C14/$C$8,"-") -> 0.99173554 | F14: EMI | G14: 0 | H14: =IFERROR($G14/$C$8,"-") -> 0 | J14: Own Health Fund | K14: 1 | L14: 32 | M14: 660000 | N14: 0 | P14: =IF(NOT(ISBLANK(Goal_Input[[#This Row],[Goal]])),IF([2]Details!$M14>0,IF(_xlfn.XLOOKUP([2]Details!$L14,'[2]Calc Engine'!$C$31:$C$66,'[2]Calc Engine'!$AO$31:$AO$66)>[2]Details!$M14,"Goal Met","Goal Not Met"),"Goal Met"),"-") -> Goal Not Met | Q14: =IF(NOT(ISBLANK(Goal_Input[[#This Row],[Goal]])),IF([2]Details!$N14>0,IF(_xlfn.XLOOKUP([2]Details!$L14,'[2]Calc Engine'!$C$31:$C$66,'[2]Calc Engine'!$AT$31:$AT$66)>[2]Details!$N14,"Goal Met","Goal Not Met"),"Goal Met"),"-") -> Goal Met | R14: =IF(NOT(ISBLANK(Goal_Input[[#This Row],[Goal]])),IF([2]Details!$O14>0,IF(_xlfn.XLOOKUP([2]Details!$L14,'[2]Calc Engine'!$C$31:$C$66,'[2]Calc Engine'!$AY$31:$AY$66)>[2]Details!$O14,"Goal Met","Goal Not Met"),"Goal Met"),"-") -> Goal Met | S14: =IF(AND(P14="Goal Met",Q14="Goal Met",R14="Goal Met"),"Goal Met",IF(ISBLANK(Goal_Input[[#This Row],[Goal]]),"-","Change Allocation")) -> Change Allocation
B15: Rent | C15: 0 | D15: =IFERROR($C15/$C$8,"-") -> 0 | F15: Entertainment | G15: 18000 | H15: =IFERROR($G15/$C$8,"-") -> 0.024793388 | J15: Marriage | K15: 1 | L15: 35 | M15: 0 | N15: 340000 | O15: 0 | P15: =IF(NOT(ISBLANK(Goal_Input[[#This Row],[Goal]])),IF([2]Details!$M15>0,IF(_xlfn.XLOOKUP([2]Details!$L15,'[2]Calc Engine'!$C$31:$C$66,'[2]Calc Engine'!$AO$31:$AO$66)>[2]Details!$M15,"Goal Met","Goal Not Met"),"Goal Met"),"-") -> Goal Met | Q15: =IF(NOT(ISBLANK(Goal_Input[[#This Row],[Goal]])),IF([2]Details!$N15>0,IF(_xlfn.XLOOKUP([2]Details!$L15,'[2]Calc Engine'!$C$31:$C$66,'[2]Calc Engine'!$AT$31:$AT$66)>[2]Details!$N15,"Goal Met","Goal Not Met"),"Goal Met"),"-") -> Goal Not Met | R15: =IF(NOT(ISBLANK(Goal_Input[[#This Row],[Goal]])),IF([2]Details!$O15>0,IF(_xlfn.XLOOKUP([2]Details!$L15,'[2]Calc Engine'!$C$31:$C$66,'[2]Calc Engine'!$AY$31:$AY$66)>[2]Details!$O15,"Goal Met","Goal Not Met"),"Goal Met"),"-") -> Goal Met | S15: =IF(AND(P15="Goal Met",Q15="Goal Met",R15="Goal Met"),"Goal Met",IF(ISBLANK(Goal_Input[[#This Row],[Goal]]),"-","Change Allocation")) -> Change Allocation
B16: Interest | C16: 6000 | D16: =IFERROR($C16/$C$8,"-") -> 0.0082644628 | F16: Food | G16: 36000 | H16: =IFERROR($G16/$C$8,"-") -> 0.049586777 | J16: Children Education | K16: 1 | L16: 42 | M16: 430000 | N16: 0 | P16: =IF(NOT(ISBLANK(Goal_Input[[#This Row],[Goal]])),IF([2]Details!$M16>0,IF(_xlfn.XLOOKUP([2]Details!$L16,'[2]Calc Engine'!$C$31:$C$66,'[2]Calc Engine'!$AO$31:$AO$66)>[2]Details!$M16,"Goal Met","Goal Not Met"),"Goal Met"),"-") -> Goal Not Met | Q16: =IF(NOT(ISBLANK(Goal_Input[[#This Row],[Goal]])),IF([2]Details!$N16>0,IF(_xlfn.XLOOKUP([2]Details!$L16,'[2]Calc Engine'!$C$31:$C$66,'[2]Calc Engine'!$AT$31:$AT$66)>[2]Details!$N16,"Goal Met","Goal Not Met"),"Goal Met"),"-") -> Goal Met | R16: =IF(NOT(ISBLANK(Goal_Input[[#This Row],[Goal]])),IF([2]Details!$O16>0,IF(_xlfn.XLOOKUP([2]Details!$L16,'[2]Calc Engine'!$C$31:$C$66,'[2]Calc Engine'!$AY$31:$AY$66)>[2]Details!$O16,"Goal Met","Goal Not Met"),"Goal Met"),"-") -> Goal Met | S16: =IF(AND(P16="Goal Met",Q16="Goal Met",R16="Goal Met"),"Goal Met",IF(ISBLANK(Goal_Input[[#This Row],[Goal]]),"-","Change Allocation")) -> Change Allocation | AB16: Chosen Scenario
B17: Business Income | C17: 0 | D17: =IFERROR($C17/$C$8,"-") -> 0 | F17: Recreation | G17: 12000 | H17: =IFERROR($G17/$C$8,"-") -> 0.016528926 | J17: House | K17: 1 | L17: 52 | M17: =6000000 -> 6000000 | N17: 0 | O17: 0 | P17: =IF(NOT(ISBLANK(Goal_Input[[#This Row],[Goal]])),IF([2]Details!$M17>0,IF(_xlfn.XLOOKUP([2]Details!$L17,'[2]Calc Engine'!$C$31:$C$66,'[2]Calc Engine'!$AO$31:$AO$66)>[2]Details!$M17,"Goal Met","Goal Not Met"),"Goal Met"),"-") -> Goal Not Met | Q17: =IF(NOT(ISBLANK(Goal_Input[[#This Row],[Goal]])),IF([2]Details!$N17>0,IF(_xlfn.XLOOKUP([2]Details!$L17,'[2]Calc Engine'!$C$31:$C$66,'[2]Calc Engine'!$AT$31:$AT$66)>[2]Details!$N17,"Goal Met","Goal Not Met"),"Goal Met"),"-") -> Goal Met | R17: =IF(NOT(ISBLANK(Goal_Input[[#This Row],[Goal]])),IF([2]Details!$O17>0,IF(_xlfn.XLOOKUP([2]Details!$L17,'[2]Calc Engine'!$C$31:$C$66,'[2]Calc Engine'!$AY$31:$AY$66)>[2]Details!$O17,"Goal Met","Goal Not Met"),"Goal Met"),"-") -> Goal Met | S17: =IF(AND(P17="Goal Met",Q17="Goal Met",R17="Goal Met"),"Goal Met",IF(ISBLANK(Goal_Input[[#This Row],[Goal]]),"-","Change Allocation")) -> Change Allocation | T17: Bank Structure | AB17: Good | AC17: =INDEX($AC$9:$AE$11,MATCH($AB17,$AB$9:$AB$11,0),MATCH($AE$13,$AC$8:$AE$8,0)) -> 0.8
B18: Other Income | C18: - | D18: =IFERROR($C18/$C$8,"-") -> - | F18: Medical expenses | G18: 6000 | H18: =IFERROR($G18/$C$8,"-") -> 0.0082644628 | J18: Car | K18: 1 | L18: 28 | M18: 0 | N18: 209000 | O18: 0 | P18: =IF(NOT(ISBLANK(Goal_Input[[#This Row],[Goal]])),IF([2]Details!$M18>0,IF(_xlfn.XLOOKUP([2]Details!$L18,'[2]Calc Engine'!$C$31:$C$66,'[2]Calc Engine'!$AO$31:$AO$66)>[2]Details!$M18,"Goal Met","Goal Not Met"),"Goal Met"),"-") -> Goal Met | Q18: =IF(NOT(ISBLANK(Goal_Input[[#This Row],[Goal]])),IF([2]Details!$N18>0,IF(_xlfn.XLOOKUP([2]Details!$L18,'[2]Calc Engine'!$C$31:$C$66,'[2]Calc Engine'!$AT$31:$AT$66)>[2]Details!$N18,"Goal Met","Goal Not Met"),"Goal Met"),"-") -> Goal Not Met | R18: =IF(NOT(ISBLANK(Goal_Input[[#This Row],[Goal]])),IF([2]Details!$O18>0,IF(_xlfn.XLOOKUP([2]Details!$L18,'[2]Calc Engine'!$C$31:$C$66,'[2]Calc Engine'!$AY$31:$AY$66)>[2]Details!$O18,"Goal Met","Goal Not Met"),"Goal Met"),"-") -> Goal Met | S18: =IF(AND(P18="Goal Met",Q18="Goal Met",R18="Goal Met"),"Goal Met",IF(ISBLANK(Goal_Input[[#This Row],[Goal]]),"-","Change Allocation")) -> Change Allocation | T18: Min Balance | V18: 100000 | AB18: Mid | AC18: =INDEX($AC$9:$AE$11,MATCH($AB18,$AB$9:$AB$11,0),MATCH($AE$13,$AC$8:$AE$8,0)) -> 0.1
F19: Luxury | G19: 24000 | H19: =IFERROR($G19/$C$8,"-") -> 0.033057851 | J19: Abroad Vacation | K19: 1 | L19: 38 | M19: 0 | N19: 0 | O19: 5500000 | P19: =IF(NOT(ISBLANK(Goal_Input[[#This Row],[Goal]])),IF([2]Details!$M19>0,IF(_xlfn.XLOOKUP([2]Details!$L19,'[2]Calc Engine'!$C$31:$C$66,'[2]Calc Engine'!$AO$31:$AO$66)>[2]Details!$M19,"Goal Met","Goal Not Met"),"Goal Met"),"-") -> Goal Met | Q19: =IF(NOT(ISBLANK(Goal_Input[[#This Row],[Goal]])),IF([2]Details!$N19>0,IF(_xlfn.XLOOKUP([2]Details!$L19,'[2]Calc Engine'!$C$31:$C$66,'[2]Calc Engine'!$AT$31:$AT$66)>[2]Details!$N19,"Goal Met","Goal Not Met"),"Goal Met"),"-") -> Goal Met | R19: =IF(NOT(ISBLANK(Goal_Input[[#This Row],[Goal]])),IF([2]Details!$O19>0,IF(_xlfn.XLOOKUP([2]Details!$L19,'[2]Calc Engine'!$C$31:$C$66,'[2]Calc Engine'!$AY$31:$AY$66)>[2]Details!$O19,"Goal Met","Goal Not Met"),"Goal Met"),"-") -> Goal Met | S19: =IF(AND(P19="Goal Met",Q19="Goal Met",R19="Goal Met"),"Goal Met",IF(ISBLANK(Goal_Input[[#This Row],[Goal]]),"-","Change Allocation")) -> Goal Met | T19: FD Amount | V19: 300000 | AB19: Worst | AC19: =INDEX($AC$9:$AE$11,MATCH($AB19,$AB$9:$AB$11,0),MATCH($AE$13,$AC$8:$AE$8,0)) -> 0.1
F20: Transportation | G20: 18000 | H20: =IFERROR($G20/$C$8,"-") -> 0.024793388 | K20: 1 | L20: 0 | M20: 0 | N20: 0 | O20: 0 | P20: =IF(NOT(ISBLANK(Goal_Input[[#This Row],[Goal]])),IF([2]Details!$M20>0,IF(_xlfn.XLOOKUP([2]Details!$L20,'[2]Calc Engine'!$C$31:$C$66,'[2]Calc Engine'!$AO$31:$AO$66)>[2]Details!$M20,"Goal Met","Goal Not Met"),"Goal Met"),"-") -> - | Q20: =IF(NOT(ISBLANK(Goal_Input[[#This Row],[Goal]])),IF([2]Details!$N20>0,IF(_xlfn.XLOOKUP([2]Details!$L20,'[2]Calc Engine'!$C$31:$C$66,'[2]Calc Engine'!$AT$31:$AT$66)>[2]Details!$N20,"Goal Met","Goal Not Met"),"Goal Met"),"-") -> - | R20: =IF(NOT(ISBLANK(Goal_Input[[#This Row],[Goal]])),IF([2]Details!$O20>0,IF(_xlfn.XLOOKUP([2]Details!$L20,'[2]Calc Engine'!$C$31:$C$66,'[2]Calc Engine'!$AY$31:$AY$66)>[2]Details!$O20,"Goal Met","Goal Not Met"),"Goal Met"),"-") -> - | S20: =IF(AND(P20="Goal Met",Q20="Goal Met",R20="Goal Met"),"Goal Met",IF(ISBLANK(Goal_Input[[#This Row],[Goal]]),"-","Change Allocation")) -> - | T20: Opening Bank Bal | V20: 80000
F21: Household Expenses | G21: 84000 | H21: =IFERROR($G21/$C$8,"-") -> 0.11570248 | K21: 1 | L21: 0 | M21: 0 | N21: 0 | O21: 0 | P21: =IF(NOT(ISBLANK(Goal_Input[[#This Row],[Goal]])),IF([2]Details!$M21>0,IF(_xlfn.XLOOKUP([2]Details!$L21,'[2]Calc Engine'!$C$31:$C$66,'[2]Calc Engine'!$AO$31:$AO$66)>[2]Details!$M21,"Goal Met","Goal Not Met"),"Goal Met"),"-") -> - | Q21: =IF(NOT(ISBLANK(Goal_Input[[#This Row],[Goal]])),IF([2]Details!$N21>0,IF(_xlfn.XLOOKUP([2]Details!$L21,'[2]Calc Engine'!$C$31:$C$66,'[2]Calc Engine'!$AT$31:$AT$66)>[2]Details!$N21,"Goal Met","Goal Not Met"),"Goal Met"),"-") -> - | R21: =IF(NOT(ISBLANK(Goal_Input[[#This Row],[Goal]])),IF([2]Details!$O21>0,IF(_xlfn.XLOOKUP([2]Details!$L21,'[2]Calc Engine'!$C$31:$C$66,'[2]Calc Engine'!$AY$31:$AY$66)>[2]Details!$O21,"Goal Met","Goal Not Met"),"Goal Met"),"-") -> - | S21: =IF(AND(P21="Goal Met",Q21="Goal Met",R21="Goal Met"),"Goal Met",IF(ISBLANK(Goal_Input[[#This Row],[Goal]]),"-","Change Allocation")) -> -
F22: Insurance | G22: 12000 | H22: =IFERROR($G22/$C$8,"-") -> 0.016528926 | K22: 1 | L22: 0 | M22: 0 | N22: 0 | O22: 0 | P22: =IF(NOT(ISBLANK(Goal_Input[[#This Row],[Goal]])),IF([2]Details!$M22>0,IF(_xlfn.XLOOKUP([2]Details!$L22,'[2]Calc Engine'!$C$31:$C$66,'[2]Calc Engine'!$AO$31:$AO$66)>[2]Details!$M22,"Goal Met","Goal Not Met"),"Goal Met"),"-") -> - | Q22: =IF(NOT(ISBLANK(Goal_Input[[#This Row],[Goal]])),IF([2]Details!$N22>0,IF(_xlfn.XLOOKUP([2]Details!$L22,'[2]Calc Engine'!$C$31:$C$66,'[2]Calc Engine'!$AT$31:$AT$66)>[2]Details!$N22,"Goal Met","Goal Not Met"),"Goal Met"),"-") -> - | R22: =IF(NOT(ISBLANK(Goal_Input[[#This Row],[Goal]])),IF([2]Details!$O22>0,IF(_xlfn.XLOOKUP([2]Details!$L22,'[2]Calc Engine'!$C$31:$C$66,'[2]Calc Engine'!$AY$31:$AY$66)>[2]Details!$O22,"Goal Met","Goal Not Met"),"Goal Met"),"-") -> - | S22: =IF(AND(P22="Goal Met",Q22="Goal Met",R22="Goal Met"),"Goal Met",IF(ISBLANK(Goal_Input[[#This Row],[Goal]]),"-","Change Allocation")) -> -
F23: Ad Hoc | G23: 24000 | H23: =IFERROR($G23/$C$8,"-") -> 0.033057851 | K23: 1 | L23: 0 | M23: 0 | N23: 0 | O23: 0 | P23: =IF(NOT(ISBLANK(Goal_Input[[#This Row],[Goal]])),IF([2]Details!$M23>0,IF(_xlfn.XLOOKUP([2]Details!$L23,'[2]Calc Engine'!$C$31:$C$66,'[2]Calc Engine'!$AO$31:$AO$66)>[2]Details!$M23,"Goal Met","Goal Not Met"),"Goal Met"),"-") -> - | Q23: =IF(NOT(ISBLANK(Goal_Input[[#This Row],[Goal]])),IF([2]Details!$N23>0,IF(_xlfn.XLOOKUP([2]Details!$L23,'[2]Calc Engine'!$C$31:$C$66,'[2]Calc Engine'!$AT$31:$AT$66)>[2]Details!$N23,"Goal Met","Goal Not Met"),"Goal Met"),"-") -> - | R23: =IF(NOT(ISBLANK(Goal_Input[[#This Row],[Goal]])),IF([2]Details!$O23>0,IF(_xlfn.XLOOKUP([2]Details!$L23,'[2]Calc Engine'!$C$31:$C$66,'[2]Calc Engine'!$AY$31:$AY$66)>[2]Details!$O23,"Goal Met","Goal Not Met"),"Goal Met"),"-") -> - | S23: =IF(AND(P23="Goal Met",Q23="Goal Met",R23="Goal Met"),"Goal Met",IF(ISBLANK(Goal_Input[[#This Row],[Goal]]),"-","Change Allocation")) -> -

Sheet Assumptions Sheet
R4: Expense Infaltion
E6: Case | F6: Probability | I6: Real Return
E7: Good | F7: =Details!AC17 -> 0.8 | H7: Growth > Inflation | I7: +
E8: Mid | F8: =Details!AC18 -> 0.1 | H8: Growth = Inflation | I8: 0
E9: Bad | F9: =Details!AC19 -> 0.1 | H9: Growth < Inflation | I9: -
E12: Growth | O12: Inflation | AA12: Investment Returns
C13: Probablities | E13: {=TRANSPOSE([1]Details!$B$14:$B$18)} -> Salary | F13: Rent | G13: Interest | H13: Business Income | I13: Other Income | O13: Inflation | P13: Food Inflation | Q13: Retail Inflation | R13: Energy Inflation | S13: Medical Inflation | T13: Household Inflation | V13: Ad Hoc Expenses | AA13: Large Cap | AB13: Mid Cap | AC13: Small Cap | AD13: FD | AE13: Savings Account
B14: {='Assumptions Sheet'!$E$7:$F$9} -> Good | C14: 0.8 | D14: =C14 -> 0.8 | E14: 0.1 | F14: 0.05 | G14: 0.05 | H14: 0.1 | I14: 0 | O14: 0.05 | P14: 0.04 | Q14: 0.08 | R14: 0.06 | S14: 0.04 | T14: =O14 -> 0.05 | V14: 10000 | X14: Probablity of Below Avg Performance | Y14: =C14 -> 0.8 | Z14: =Y14 -> 0.8 | AA14: 0.14 | AB14: 0.16 | AC14: 0.2 | AD14: 0.05 | AE14: 0.03
B15: Mid | C15: 0.1 | D15: =SUM(C14:C15) -> 0.9 | E15: 0.07 | F15: 0.05 | G15: 0.05 | H15: 0.05 | I15: 0 | O15: 0.06 | P15: 0.05 | Q15: 0.05 | R15: 0.06 | S15: 0.04 | T15: 0.04 | V15: 15000 | X15: Probablity of Avg Performance | Y15: =C15 -> 0.1 | Z15: =SUM(Y14:Y15) -> 0.9 | AA15: 0.12 | AB15: 0.14 | AC15: 0.16 | AD15: 0.05 | AE15: 0.03
B16: Bad | C16: 0.1 | D16: =SUM(C14:C16) -> 1 | E16: 0.04 | F16: 0.05 | G16: 0.05 | H16: 0.01 | I16: 0 | O16: 0.08 | P16: 0.07 | Q16: 0.1 | R16: 0.06 | S16: 0.04 | T16: 0.08 | V16: 30000 | X16: Porbablity of Above Avg | Y16: =C16 -> 0.1 | Z16: =SUM(Y14:Y16) -> 1 | AA16: 0.09 | AB16: 0.12 | AC16: 0.14 | AD16: 0.05 | AE16: 0.03
E20: =E13 -> Salary | F20: =F13 -> Rent | G20: =G13 -> Interest | H20: =H13 -> Business Income | I20: =I13 -> Other Income | O20: General Expense | P20: Food | Q20: Retail Purchases | R20: Transport | S20: Medical Expenses | T20: Household Expenses | U20: Insurance | AA20: =AA13 -> Large Cap | AB20: =AB13 -> Mid Cap | AC20: =AC13 -> Small Cap | AD20: =AD13 -> FD | AE20: =AE13 -> Savings Account
A21: {=_xlfn.SEQUENCE([1]Details!C4-[1]Details!C3,1,[1]Details!C3,1)} -> 20 | B21: 0.47881104 | C21: =RAND() -> 0.92532471 | E21: {=_xlfn.IFS($C21<$D$14,E$14, $C21<$D$15,E$15, $C21<$D$16,E$16)} -> 0.04 | F21: {=_xlfn.IFS($C21<$D$14,F$14, $C21<$D$15,F$15, $C21<$D$16,F$16)} -> 0.05 | G21: {=_xlfn.IFS($C21<$D$14,G$14, $C21<$D$15,G$15, $C21<$D$16,G$16)} -> 0.05 | H21: {=_xlfn.IFS($C21<$D$14,H$14, $C21<$D$15,H$15, $C21<$D$16,H$16)} -> 0.01 | I21: {=_xlfn.IFS($C21<$D$14,I$14, $C21<$D$15,I$15, $C21<$D$16,I$16)} -> 0 | O21: {=_xlfn.IFS($C21<$D$14,O$14, $C21<$D$15,O$15, $C21<$D$16,O$16)} -> 0.08 | P21: {=_xlfn.IFS($C21<$D$14,P$14, $C21<$D$15,P$15, $C21<$D$16,P$16)} -> 0.07 | Q21: {=_xlfn.IFS($C21<$D$14,Q$14, $C21<$D$15,Q$15, $C21<$D$16,Q$16)} -> 0.1 | R21: {=_xlfn.IFS($C21<$D$14,R$14, $C21<$D$15,R$15, $C21<$D$16,R$16)} -> 0.06 | S21: {=_xlfn.IFS($C21<$D$14,S$14, $C21<$D$15,S$15, $C21<$D$16,S$16)} -> 0.04 | T21: {=_xlfn.IFS($C21<$D$14,T$14, $C21<$D$15,T$15, $C21<$D$16,T$16)} -> 0.08 | U21: {=_xlfn.IFS($C21<$D$14,U$14, $C21<$D$15,U$15, $C21<$D$16,U$16)} -> 0 | V21: {=_xlfn.IFS($C21<$D$14,V$14, $C21<$D$15,V$15, $C21<$D$16,V$16)} -> 30000 | AA21: {=_xlfn.IFS($C21<$Z$14,AA$14, $C21<$Z$15,AA$15, $C21<$Z$16,AA$16)} -> 0.09 | AB21: {=_xlfn.IFS($C21<$Z$14,AB$14, $C21<$Z$15,AB$15, $C21<$Z$16,AB$16)} -> 0.12 | AC21: {=_xlfn.IFS($C21<$Z$14,AC$14, $C21<$Z$15,AC$15, $C21<$Z$16,AC$16)} -> 0.14 | AD21: {=_xlfn.IFS($C21<$Z$14,AD$14, $C21<$Z$15,AD$15, $C21<$Z$16,AD$16)} -> 0.05 | AE21: {=_xlfn.IFS($C21<$Z$14,AE$14, $C21<$Z$15,AE$15, $C21<$Z$16,AE$16)} -> 0.03
A22: 21 | B22: 0.024462289 | C22: =RAND() -> 0.76031527 | E22: {=_xlfn.IFS($C22<$D$14,E$14, $C22<$D$15,E$15, $C22<$D$16,E$16)} -> 0.1 | F22: {=_xlfn.IFS($C22<$D$14,F$14, $C22<$D$15,F$15, $C22<$D$16,F$16)} -> 0.05 | G22: {=_xlfn.IFS($C22<$D$14,G$14, $C22<$D$15,G$15, $C22<$D$16,G$16)} -> 0.05 | H22: {=_xlfn.IFS($C22<$D$14,H$14, $C22<$D$15,H$15, $C22<$D$16,H$16)} -> 0.1 | I22: {=_xlfn.IFS($C22<$D$14,I$14, $C22<$D$15,I$15, $C22<$D$16,I$16)} -> 0 | O22: {=_xlfn.IFS($C22<$D$14,O$14, $C22<$D$15,O$15, $C22<$D$16,O$16)} -> 0.05 | P22: {=_xlfn.IFS($C22<$D$14,P$14, $C22<$D$15,P$15, $C22<$D$16,P$16)} -> 0.04 | Q22: {=_xlfn.IFS($C22<$D$14,Q$14, $C22<$D$15,Q$15, $C22<$D$16,Q$16)} -> 0.08 | R22: {=_xlfn.IFS($C22<$D$14,R$14, $C22<$D$15,R$15, $C22<$D$16,R$16)} -> 0.06 | S22: {=_xlfn.IFS($C22<$D$14,S$14, $C22<$D$15,S$15, $C22<$D$16,S$16)} -> 0.04 | T22: {=_xlfn.IFS($C22<$D$14,T$14, $C22<$D$15,T$15, $C22<$D$16,T$16)} -> 0.05 | U22: {=_xlfn.IFS($C22<$D$14,U$14, $C22<$D$15,U$15, $C22<$D$16,U$16)} -> 0 | V22: {=_xlfn.IFS($C22<$D$14,V$14, $C22<$D$15,V$15, $C22<$D$16,V$16)} -> 10000 | AA22: {=_xlfn.IFS($C22<$Z$14,AA$14, $C22<$Z$15,AA$15, $C22<$Z$16,AA$16)} -> 0.14 | AB22: {=_xlfn.IFS($C22<$Z$14,AB$14, $C22<$Z$15,AB$15, $C22<$Z$16,AB$16)} -> 0.16 | AC22: {=_xlfn.IFS($C22<$Z$14,AC$14, $C22<$Z$15,AC$15, $C22<$Z$16,AC$16)} -> 0.2 | AD22: {=_xlfn.IFS($C22<$Z$14,AD$14, $C22<$Z$15,AD$15, $C22<$Z$16,AD$16)} -> 0.05 | AE22: {=_xlfn.IFS($C22<$Z$14,AE$14, $C22<$Z$15,AE$15, $C22<$Z$16,AE$16)} -> 0.03
A23: 22 | B23: 0.71732593 | C23: =RAND() -> 0.88287925 | E23: {=_xlfn.IFS($C23<$D$14,E$14, $C23<$D$15,E$15, $C23<$D$16,E$16)} -> 0.07 | F23: {=_xlfn.IFS($C23<$D$14,F$14, $C23<$D$15,F$15, $C23<$D$16,F$16)} -> 0.05 | G23: {=_xlfn.IFS($C23<$D$14,G$14, $C23<$D$15,G$15, $C23<$D$16,G$16)} -> 0.05 | H23: {=_xlfn.IFS($C23<$D$14,H$14, $C23<$D$15,H$15, $C23<$D$16,H$16)} -> 0.05 | I23: {=_xlfn.IFS($C23<$D$14,I$14, $C23<$D$15,I$15, $C23<$D$16,I$16)} -> 0 | O23: {=_xlfn.IFS($C23<$D$14,O$14, $C23<$D$15,O$15, $C23<$D$16,O$16)} -> 0.06 | P23: {=_xlfn.IFS($C23<$D$14,P$14, $C23<$D$15,P$15, $C23<$D$16,P$16)} -> 0.05 | Q23: {=_xlfn.IFS($C23<$D$14,Q$14, $C23<$D$15,Q$15, $C23<$D$16,Q$16)} -> 0.05 | R23: {=_xlfn.IFS($C23<$D$14,R$14, $C23<$D$15,R$15, $C23<$D$16,R$16)} -> 0.06 | S23: {=_xlfn.IFS($C23<$D$14,S$14, $C23<$D$15,S$15, $C23<$D$16,S$16)} -> 0.04 | T23: {=_xlfn.IFS($C23<$D$14,T$14, $C23<$D$15,T$15, $C23<$D$16,T$16)} -> 0.04 | U23: {=_xlfn.IFS($C23<$D$14,U$14, $C23<$D$15,U$15, $C23<$D$16,U$16)} -> 0 | V23: {=_xlfn.IFS($C23<$D$14,V$14, $C23<$D$15,V$15, $C23<$D$16,V$16)} -> 15000 | AA23: {=_xlfn.IFS($C23<$Z$14,AA$14, $C23<$Z$15,AA$15, $C23<$Z$16,AA$16)} -> 0.12 | AB23: {=_xlfn.IFS($C23<$Z$14,AB$14, $C23<$Z$15,AB$15, $C23<$Z$16,AB$16)} -> 0.14 | AC23: {=_xlfn.IFS($C23<$Z$14,AC$14, $C23<$Z$15,AC$15, $C23<$Z$16,AC$16)} -> 0.16 | AD23: {=_xlfn.IFS($C23<$Z$14,AD$14, $C23<$Z$15,AD$15, $C23<$Z$16,AD$16)} -> 0.05 | AE23: {=_xlfn.IFS($C23<$Z$14,AE$14, $C23<$Z$15,AE$15, $C23<$Z$16,AE$16)} -> 0.03
A24: 23 | B24: 0.57865858 | C24: =RAND() -> 0.047902914 | E24: {=_xlfn.IFS($C24<$D$14,E$14, $C24<$D$15,E$15, $C24<$D$16,E$16)} -> 0.1 | F24: {=_xlfn.IFS($C24<$D$14,F$14, $C24<$D$15,F$15, $C24<$D$16,F$16)} -> 0.05 | G24: {=_xlfn.IFS($C24<$D$14,G$14, $C24<$D$15,G$15, $C24<$D$16,G$16)} -> 0.05 | H24: {=_xlfn.IFS($C24<$D$14,H$14, $C24<$D$15,H$15, $C24<$D$16,H$16)} -> 0.1 | I24: {=_xlfn.IFS($C24<$D$14,I$14, $C24<$D$15,I$15, $C24<$D$16,I$16)} -> 0 | O24: {=_xlfn.IFS($C24<$D$14,O$14, $C24<$D$15,O$15, $C24<$D$16,O$16)} -> 0.05 | P24: {=_xlfn.IFS($C24<$D$14,P$14, $C24<$D$15,P$15, $C24<$D$16,P$16)} -> 0.04 | Q24: {=_xlfn.IFS($C24<$D$14,Q$14, $C24<$D$15,Q$15, $C24<$D$16,Q$16)} -> 0.08 | R24: {=_xlfn.IFS($C24<$D$14,R$14, $C24<$D$15,R$15, $C24<$D$16,R$16)} -> 0.06 | S24: {=_xlfn.IFS($C24<$D$14,S$14, $C24<$D$15,S$15, $C24<$D$16,S$16)} -> 0.04 | T24: {=_xlfn.IFS($C24<$D$14,T$14, $C24<$D$15,T$15, $C24<$D$16,T$16)} -> 0.05 | U24: {=_xlfn.IFS($C24<$D$14,U$14, $C24<$D$15,U$15, $C24<$D$16,U$16)} -> 0 | V24: {=_xlfn.IFS($C24<$D$14,V$14, $C24<$D$15,V$15, $C24<$D$16,V$16)} -> 10000 | AA24: {=_xlfn.IFS($C24<$Z$14,AA$14, $C24<$Z$15,AA$15, $C24<$Z$16,AA$16)} -> 0.14 | AB24: {=_xlfn.IFS($C24<$Z$14,AB$14, $C24<$Z$15,AB$15, $C24<$Z$16,AB$16)} -> 0.16 | AC24: {=_xlfn.IFS($C24<$Z$14,AC$14, $C24<$Z$15,AC$15, $C24<$Z$16,AC$16)} -> 0.2 | AD24: {=_xlfn.IFS($C24<$Z$14,AD$14, $C24<$Z$15,AD$15, $C24<$Z$16,AD$16)} -> 0.05 | AE24: {=_xlfn.IFS($C24<$Z$14,AE$14, $C24<$Z$15,AE$15, $C24<$Z$16,AE$16)} -> 0.03
A25: 24 | B25: 0.94896113 | C25: =RAND() -> 0.31357845 | E25: {=_xlfn.IFS($C25<$D$14,E$14, $C25<$D$15,E$15, $C25<$D$16,E$16)} -> 0.1 | F25: {=_xlfn.IFS($C25<$D$14,F$14, $C25<$D$15,F$15, $C25<$D$16,F$16)} -> 0.05 | G25: {=_xlfn.IFS($C25<$D$14,G$14, $C25<$D$15,G$15, $C25<$D$16,G$16)} -> 0.05 | H25: {=_xlfn.IFS($C25<$D$14,H$14, $C25<$D$15,H$15, $C25<$D$16,H$16)} -> 0.1 | I25: {=_xlfn.IFS($C25<$D$14,I$14, $C25<$D$15,I$15, $C25<$D$16,I$16)} -> 0 | O25: {=_xlfn.IFS($C25<$D$14,O$14, $C25<$D$15,O$15, $C25<$D$16,O$16)} -> 0.05 | P25: {=_xlfn.IFS($C25<$D$14,P$14, $C25<$D$15,P$15, $C25<$D$16,P$16)} -> 0.04 | Q25: {=_xlfn.IFS($C25<$D$14,Q$14, $C25<$D$15,Q$15, $C25<$D$16,Q$16)} -> 0.08 | R25: {=_xlfn.IFS($C25<$D$14,R$14, $C25<$D$15,R$15, $C25<$D$16,R$16)} -> 0.06 | S25: {=_xlfn.IFS($C25<$D$14,S$14, $C25<$D$15,S$15, $C25<$D$16,S$16)} -> 0.04 | T25: {=_xlfn.IFS($C25<$D$14,T$14, $C25<$D$15,T$15, $C25<$D$16,T$16)} -> 0.05 | U25: {=_xlfn.IFS($C25<$D$14,U$14, $C25<$D$15,U$15, $C25<$D$16,U$16)} -> 0 | V25: {=_xlfn.IFS($C25<$D$14,V$14, $C25<$D$15,V$15, $C25<$D$16,V$16)} -> 10000 | AA25: {=_xlfn.IFS($C25<$Z$14,AA$14, $C25<$Z$15,AA$15, $C25<$Z$16,AA$16)} -> 0.14 | AB25: {=_xlfn.IFS($C25<$Z$14,AB$14, $C25<$Z$15,AB$15, $C25<$Z$16,AB$16)} -> 0.16 | AC25: {=_xlfn.IFS($C25<$Z$14,AC$14, $C25<$Z$15,AC$15, $C25<$Z$16,AC$16)} -> 0.2 | AD25: {=_xlfn.IFS($C25<$Z$14,AD$14, $C25<$Z$15,AD$15, $C25<$Z$16,AD$16)} -> 0.05 | AE25: {=_xlfn.IFS($C25<$Z$14,AE$14, $C25<$Z$15,AE$15, $C25<$Z$16,AE$16)} -> 0.03
A26: 25 | B26: 0.36965764 | C26: =RAND() -> 0.97183118 | E26: {=_xlfn.IFS($C26<$D$14,E$14, $C26<$D$15,E$15, $C26<$D$16,E$16)} -> 0.04 | F26: {=_xlfn.IFS($C26<$D$14,F$14, $C26<$D$15,F$15, $C26<$D$16,F$16)} -> 0.05 | G26: {=_xlfn.IFS($C26<$D$14,G$14, $C26<$D$15,G$15, $C26<$D$16,G$16)} -> 0.05 | H26: {=_xlfn.IFS($C26<$D$14,H$14, $C26<$D$15,H$15, $C26<$D$16,H$16)} -> 0.01 | I26: {=_xlfn.IFS($C26<$D$14,I$14, $C26<$D$15,I$15, $C26<$D$16,I$16)} -> 0 | O26: {=_xlfn.IFS($C26<$D$14,O$14, $C26<$D$15,O$15, $C26<$D$16,O$16)} -> 0.08 | P26: {=_xlfn.IFS($C26<$D$14,P$14, $C26<$D$15,P$15, $C26<$D$16,P$16)} -> 0.07 | Q26: {=_xlfn.IFS($C26<$D$14,Q$14, $C26<$D$15,Q$15, $C26<$D$16,Q$16)} -> 0.1 | R26: {=_xlfn.IFS($C26<$D$14,R$14, $C26<$D$15,R$15, $C26<$D$16,R$16)} -> 0.06 | S26: {=_xlfn.IFS($C26<$D$14,S$14, $C26<$D$15,S$15, $C26<$D$16,S$16)} -> 0.04 | T26: {=_xlfn.IFS($C26<$D$14,T$14, $C26<$D$15,T$15, $C26<$D$16,T$16)} -> 0.08 | U26: {=_xlfn.IFS($C26<$D$14,U$14, $C26<$D$15,U$15, $C26<$D$16,U$16)} -> 0 | V26: {=_xlfn.IFS($C26<$D$14,V$14, $C26<$D$15,V$15, $C26<$D$16,V$16)} -> 30000 | AA26: {=_xlfn.IFS($C26<$Z$14,AA$14, $C26<$Z$15,AA$15, $C26<$Z$16,AA$16)} -> 0.09 | AB26: {=_xlfn.IFS($C26<$Z$14,AB$14, $C26<$Z$15,AB$15, $C26<$Z$16,AB$16)} -> 0.12 | AC26: {=_xlfn.IFS($C26<$Z$14,AC$14, $C26<$Z$15,AC$15, $C26<$Z$16,AC$16)} -> 0.14 | AD26: {=_xlfn.IFS($C26<$Z$14,AD$14, $C26<$Z$15,AD$15, $C26<$Z$16,AD$16)} -> 0.05 | AE26: {=_xlfn.IFS($C26<$Z$14,AE$14, $C26<$Z$15,AE$15, $C26<$Z$16,AE$16)} -> 0.03
A27: 26 | B27: 0.77762074 | C27: =RAND() -> 0.40933402 | E27: {=_xlfn.IFS($C27<$D$14,E$14, $C27<$D$15,E$15, $C27<$D$16,E$16)} -> 0.1 | F27: {=_xlfn.IFS($C27<$D$14,F$14, $C27<$D$15,F$15, $C27<$D$16,F$16)} -> 0.05 | G27: {=_xlfn.IFS($C27<$D$14,G$14, $C27<$D$15,G$15, $C27<$D$16,G$16)} -> 0.05 | H27: {=_xlfn.IFS($C27<$D$14,H$14, $C27<$D$15,H$15, $C27<$D$16,H$16)} -> 0.1 | I27: {=_xlfn.IFS($C27<$D$14,I$14, $C27<$D$15,I$15, $C27<$D$16,I$16)} -> 0 | O27: {=_xlfn.IFS($C27<$D$14,O$14, $C27<$D$15,O$15, $C27<$D$16,O$16)} -> 0.05 | P27: {=_xlfn.IFS($C27<$D$14,P$14, $C27<$D$15,P$15, $C27<$D$16,P$16)} -> 0.04 | Q27: {=_xlfn.IFS($C27<$D$14,Q$14, $C27<$D$15,Q$15, $C27<$D$16,Q$16)} -> 0.08 | R27: {=_xlfn.IFS($C27<$D$14,R$14, $C27<$D$15,R$15, $C27<$D$16,R$16)} -> 0.06 | S27: {=_xlfn.IFS($C27<$D$14,S$14, $C27<$D$15,S$15, $C27<$D$16,S$16)} -> 0.04 | T27: {=_xlfn.IFS($C27<$D$14,T$14, $C27<$D$15,T$15, $C27<$D$16,T$16)} -> 0.05 | U27: {=_xlfn.IFS($C27<$D$14,U$14, $C27<$D$15,U$15, $C27<$D$16,U$16)} -> 0 | V27: {=_xlfn.IFS($C27<$D$14,V$14, $C27<$D$15,V$15, $C27<$D$16,V$16)} -> 10000 | AA27: {=_xlfn.IFS($C27<$Z$14,AA$14, $C27<$Z$15,AA$15, $C27<$Z$16,AA$16)} -> 0.14 | AB27: {=_xlfn.IFS($C27<$Z$14,AB$14, $C27<$Z$15,AB$15, $C27<$Z$16,AB$16)} -> 0.16 | AC27: {=_xlfn.IFS($C27<$Z$14,AC$14, $C27<$Z$15,AC$15, $C27<$Z$16,AC$16)} -> 0.2 | AD27: {=_xlfn.IFS($C27<$Z$14,AD$14, $C27<$Z$15,AD$15, $C27<$Z$16,AD$16)} -> 0.05 | AE27: {=_xlfn.IFS($C27<$Z$14,AE$14, $C27<$Z$15,AE$15, $C27<$Z$16,AE$16)} -> 0.03
A28: 27 | B28: 0.022391029 | C28: =RAND() -> 0.72790364 | E28: {=_xlfn.IFS($C28<$D$14,E$14, $C28<$D$15,E$15, $C28<$D$16,E$16)} -> 0.1 | F28: {=_xlfn.IFS($C28<$D$14,F$14, $C28<$D$15,F$15, $C28<$D$16,F$16)} -> 0.05 | G28: {=_xlfn.IFS($C28<$D$14,G$14, $C28<$D$15,G$15, $C28<$D$16,G$16)} -> 0.05 | H28: {=_xlfn.IFS($C28<$D$14,H$14, $C28<$D$15,H$15, $C28<$D$16,H$16)} -> 0.1 | I28: {=_xlfn.IFS($C28<$D$14,I$14, $C28<$D$15,I$15, $C28<$D$16,I$16)} -> 0 | O28: {=_xlfn.IFS($C28<$D$14,O$14, $C28<$D$15,O$15, $C28<$D$16,O$16)} -> 0.05 | P28: {=_xlfn.IFS($C28<$D$14,P$14, $C28<$D$15,P$15, $C28<$D$16,P$16)} -> 0.04 | Q28: {=_xlfn.IFS($C28<$D$14,Q$14, $C28<$D$15,Q$15, $C28<$D$16,Q$16)} -> 0.08 | R28: {=_xlfn.IFS($C28<$D$14,R$14, $C28<$D$15,R$15, $C28<$D$16,R$16)} -> 0.06 | S28: {=_xlfn.IFS($C28<$D$14,S$14, $C28<$D$15,S$15, $C28<$D$16,S$16)} -> 0.04 | T28: {=_xlfn.IFS($C28<$D$14,T$14, $C28<$D$15,T$15, $C28<$D$16,T$16)} -> 0.05 | U28: {=_xlfn.IFS($C28<$D$14,U$14, $C28<$D$15,U$15, $C28<$D$16,U$16)} -> 0 | V28: {=_xlfn.IFS($C28<$D$14,V$14, $C28<$D$15,V$15, $C28<$D$16,V$16)} -> 10000 | AA28: {=_xlfn.IFS($C28<$Z$14,AA$14, $C28<$Z$15,AA$15, $C28<$Z$16,AA$16)} -> 0.14 | AB28: {=_xlfn.IFS($C28<$Z$14,AB$14, $C28<$Z$15,AB$15, $C28<$Z$16,AB$16)} -> 0.16 | AC28: {=_xlfn.IFS($C28<$Z$14,AC$14, $C28<$Z$15,AC$15, $C28<$Z$16,AC$16)} -> 0.2 | AD28: {=_xlfn.IFS($C28<$Z$14,AD$14, $C28<$Z$15,AD$15, $C28<$Z$16,AD$16)} -> 0.05 | AE28: {=_xlfn.IFS($C28<$Z$14,AE$14, $C28<$Z$15,AE$15, $C28<$Z$16,AE$16)} -> 0.03
A29: 28 | B29: 0.60634937 | C29: =RAND() -> 0.67431708 | E29: {=_xlfn.IFS($C29<$D$14,E$14, $C29<$D$15,E$15, $C29<$D$16,E$16)} -> 0.1 | F29: {=_xlfn.IFS($C29<$D$14,F$14, $C29<$D$15,F$15, $C29<$D$16,F$16)} -> 0.05 | G29: {=_xlfn.IFS($C29<$D$14,G$14, $C29<$D$15,G$15, $C29<$D$16,G$16)} -> 0.05 | H29: {=_xlfn.IFS($C29<$D$14,H$14, $C29<$D$15,H$15, $C29<$D$16,H$16)} -> 0.1 | I29: {=_xlfn.IFS($C29<$D$14,I$14, $C29<$D$15,I$15, $C29<$D$16,I$16)} -> 0 | O29: {=_xlfn.IFS($C29<$D$14,O$14, $C29<$D$15,O$15, $C29<$D$16,O$16)} -> 0.05 | P29: {=_xlfn.IFS($C29<$D$14,P$14, $C29<$D$15,P$15, $C29<$D$16,P$16)} -> 0.04 | Q29: {=_xlfn.IFS($C29<$D$14,Q$14, $C29<$D$15,Q$15, $C29<$D$16,Q$16)} -> 0.08 | R29: {=_xlfn.IFS($C29<$D$14,R$14, $C29<$D$15,R$15, $C29<$D$16,R$16)} -> 0.06 | S29: {=_xlfn.IFS($C29<$D$14,S$14, $C29<$D$15,S$15, $C29<$D$16,S$16)} -> 0.04 | T29: {=_xlfn.IFS($C29<$D$14,T$14, $C29<$D$15,T$15, $C29<$D$16,T$16)} -> 0.05 | U29: {=_xlfn.IFS($C29<$D$14,U$14, $C29<$D$15,U$15, $C29<$D$16,U$16)} -> 0 | V29: {=_xlfn.IFS($C29<$D$14,V$14, $C29<$D$15,V$15, $C29<$D$16,V$16)} -> 10000 | AA29: {=_xlfn.IFS($C29<$Z$14,AA$14, $C29<$Z$15,AA$15, $C29<$Z$16,AA$16)} -> 0.14 | AB29: {=_xlfn.IFS($C29<$Z$14,AB$14, $C29<$Z$15,AB$15, $C29<$Z$16,AB$16)} -> 0.16 | AC29: {=_xlfn.IFS($C29<$Z$14,AC$14, $C29<$Z$15,AC$15, $C29<$Z$16,AC$16)} -> 0.2 | AD29: {=_xlfn.IFS($C29<$Z$14,AD$14, $C29<$Z$15,AD$15, $C29<$Z$16,AD$16)} -> 0.05 | AE29: {=_xlfn.IFS($C29<$Z$14,AE$14, $C29<$Z$15,AE$15, $C29<$Z$16,AE$16)} -> 0.03
A30: 29 | B30: 0.46050695 | C30: =RAND() -> 0.70938432 | E30: {=_xlfn.IFS($C30<$D$14,E$14, $C30<$D$15,E$15, $C30<$D$16,E$16)} -> 0.1 | F30: {=_xlfn.IFS($C30<$D$14,F$14, $C30<$D$15,F$15, $C30<$D$16,F$16)} -> 0.05 | G30: {=_xlfn.IFS($C30<$D$14,G$14, $C30<$D$15,G$15, $C30<$D$16,G$16)} -> 0.05 | H30: {=_xlfn.IFS($C30<$D$14,H$14, $C30<$D$15,H$15, $C30<$D$16,H$16)} -> 0.1 | I30: {=_xlfn.IFS($C30<$D$14,I$14, $C30<$D$15,I$15, $C30<$D$16,I$16)} -> 0 | O30: {=_xlfn.IFS($C30<$D$14,O$14, $C30<$D$15,O$15, $C30<$D$16,O$16)} -> 0.05 | P30: {=_xlfn.IFS($C30<$D$14,P$14, $C30<$D$15,P$15, $C30<$D$16,P$16)} -> 0.04 | Q30: {=_xlfn.IFS($C30<$D$14,Q$14, $C30<$D$15,Q$15, $C30<$D$16,Q$16)} -> 0.08 | R30: {=_xlfn.IFS($C30<$D$14,R$14, $C30<$D$15,R$15, $C30<$D$16,R$16)} -> 0.06 | S30: {=_xlfn.IFS($C30<$D$14,S$14, $C30<$D$15,S$15, $C30<$D$16,S$16)} -> 0.04 | T30: {=_xlfn.IFS($C30<$D$14,T$14, $C30<$D$15,T$15, $C30<$D$16,T$16)} -> 0.05 | U30: {=_xlfn.IFS($C30<$D$14,U$14, $C30<$D$15,U$15, $C30<$D$16,U$16)} -> 0 | V30: {=_xlfn.IFS($C30<$D$14,V$14, $C30<$D$15,V$15, $C30<$D$16,V$16)} -> 10000 | AA30: {=_xlfn.IFS($C30<$Z$14,AA$14, $C30<$Z$15,AA$15, $C30<$Z$16,AA$16)} -> 0.14 | AB30: {=_xlfn.IFS($C30<$Z$14,AB$14, $C30<$Z$15,AB$15, $C30<$Z$16,AB$16)} -> 0.16 | AC30: {=_xlfn.IFS($C30<$Z$14,AC$14, $C30<$Z$15,AC$15, $C30<$Z$16,AC$16)} -> 0.2 | AD30: {=_xlfn.IFS($C30<$Z$14,AD$14, $C30<$Z$15,AD$15, $C30<$Z$16,AD$16)} -> 0.05 | AE30: {=_xlfn.IFS($C30<$Z$14,AE$14, $C30<$Z$15,AE$15, $C30<$Z$16,AE$16)} -> 0.03
A31: 30 | B31: 0.60175563 | C31: =RAND() -> 0.87310294 | E31: {=_xlfn.IFS($C31<$D$14,E$14, $C31<$D$15,E$15, $C31<$D$16,E$16)} -> 0.07 | F31: {=_xlfn.IFS($C31<$D$14,F$14, $C31<$D$15,F$15, $C31<$D$16,F$16)} -> 0.05 | G31: {=_xlfn.IFS($C31<$D$14,G$14, $C31<$D$15,G$15, $C31<$D$16,G$16)} -> 0.05 | H31: {=_xlfn.IFS($C31<$D$14,H$14, $C31<$D$15,H$15, $C31<$D$16,H$16)} -> 0.05 | I31: {=_xlfn.IFS($C31<$D$14,I$14, $C31<$D$15,I$15, $C31<$D$16,I$16)} -> 0 | O31: {=_xlfn.IFS($C31<$D$14,O$14, $C31<$D$15,O$15, $C31<$D$16,O$16)} -> 0.06 | P31: {=_xlfn.IFS($C31<$D$14,P$14, $C31<$D$15,P$15, $C31<$D$16,P$16)} -> 0.05 | Q31: {=_xlfn.IFS($C31<$D$14,Q$14, $C31<$D$15,Q$15, $C31<$D$16,Q$16)} -> 0.05 | R31: {=_xlfn.IFS($C31<$D$14,R$14, $C31<$D$15,R$15, $C31<$D$16,R$16)} -> 0.06 | S31: {=_xlfn.IFS($C31<$D$14,S$14, $C31<$D$15,S$15, $C31<$D$16,S$16)} -> 0.04 | T31: {=_xlfn.IFS($C31<$D$14,T$14, $C31<$D$15,T$15, $C31<$D$16,T$16)} -> 0.04 | U31: {=_xlfn.IFS($C31<$D$14,U$14, $C31<$D$15,U$15, $C31<$D$16,U$16)} -> 0 | V31: {=_xlfn.IFS($C31<$D$14,V$14, $C31<$D$15,V$15, $C31<$D$16,V$16)} -> 15000 | AA31: {=_xlfn.IFS($C31<$Z$14,AA$14, $C31<$Z$15,AA$15, $C31<$Z$16,AA$16)} -> 0.12 | AB31: {=_xlfn.IFS($C31<$Z$14,AB$14, $C31<$Z$15,AB$15, $C31<$Z$16,AB$16)} -> 0.14 | AC31: {=_xlfn.IFS($C31<$Z$14,AC$14, $C31<$Z$15,AC$15, $C31<$Z$16,AC$16)} -> 0.16 | AD31: {=_xlfn.IFS($C31<$Z$14,AD$14, $C31<$Z$15,AD$15, $C31<$Z$16,AD$16)} -> 0.05 | AE31: {=_xlfn.IFS($C31<$Z$14,AE$14, $C31<$Z$15,AE$15, $C31<$Z$16,AE$16)} -> 0.03
A32: 31 | B32: 0.83464744 | C32: =RAND() -> 0.34060992 | E32: {=_xlfn.IFS($C32<$D$14,E$14, $C32<$D$15,E$15, $C32<$D$16,E$16)} -> 0.1 | F32: {=_xlfn.IFS($C32<$D$14,F$14, $C32<$D$15,F$15, $C32<$D$16,F$16)} -> 0.05 | G32: {=_xlfn.IFS($C32<$D$14,G$14, $C32<$D$15,G$15, $C32<$D$16,G$16)} -> 0.05 | H32: {=_xlfn.IFS($C32<$D$14,H$14, $C32<$D$15,H$15, $C32<$D$16,H$16)} -> 0.1 | I32: {=_xlfn.IFS($C32<$D$14,I$14, $C32<$D$15,I$15, $C32<$D$16,I$16)} -> 0 | O32: {=_xlfn.IFS($C32<$D$14,O$14, $C32<$D$15,O$15, $C32<$D$16,O$16)} -> 0.05 | P32: {=_xlfn.IFS($C32<$D$14,P$14, $C32<$D$15,P$15, $C32<$D$16,P$16)} -> 0.04 | Q32: {=_xlfn.IFS($C32<$D$14,Q$14, $C32<$D$15,Q$15, $C32<$D$16,Q$16)} -> 0.08 | R32: {=_xlfn.IFS($C32<$D$14,R$14, $C32<$D$15,R$15, $C32<$D$16,R$16)} -> 0.06 | S32: {=_xlfn.IFS($C32<$D$14,S$14, $C32<$D$15,S$15, $C32<$D$16,S$16)} -> 0.04 | T32: {=_xlfn.IFS($C32<$D$14,T$14, $C32<$D$15,T$15, $C32<$D$16,T$16)} -> 0.05 | U32: {=_xlfn.IFS($C32<$D$14,U$14, $C32<$D$15,U$15, $C32<$D$16,U$16)} -> 0 | V32: {=_xlfn.IFS($C32<$D$14,V$14, $C32<$D$15,V$15, $C32<$D$16,V$16)} -> 10000 | AA32: {=_xlfn.IFS($C32<$Z$14,AA$14, $C32<$Z$15,AA$15, $C32<$Z$16,AA$16)} -> 0.14 | AB32: {=_xlfn.IFS($C32<$Z$14,AB$14, $C32<$Z$15,AB$15, $C32<$Z$16,AB$16)} -> 0.16 | AC32: {=_xlfn.IFS($C32<$Z$14,AC$14, $C32<$Z$15,AC$15, $C32<$Z$16,AC$16)} -> 0.2 | AD32: {=_xlfn.IFS($C32<$Z$14,AD$14, $C32<$Z$15,AD$15, $C32<$Z$16,AD$16)} -> 0.05 | AE32: {=_xlfn.IFS($C32<$Z$14,AE$14, $C32<$Z$15,AE$15, $C32<$Z$16,AE$16)} -> 0.03
A33: 32 | B33: 0.69922046 | C33: =RAND() -> 0.034965093 | E33: {=_xlfn.IFS($C33<$D$14,E$14, $C33<$D$15,E$15, $C33<$D$16,E$16)} -> 0.1 | F33: {=_xlfn.IFS($C33<$D$14,F$14, $C33<$D$15,F$15, $C33<$D$16,F$16)} -> 0.05 | G33: {=_xlfn.IFS($C33<$D$14,G$14, $C33<$D$15,G$15, $C33<$D$16,G$16)} -> 0.05 | H33: {=_xlfn.IFS($C33<$D$14,H$14, $C33<$D$15,H$15, $C33<$D$16,H$16)} -> 0.1 | I33: {=_xlfn.IFS($C33<$D$14,I$14, $C33<$D$15,I$15, $C33<$D$16,I$16)} -> 0 | O33: {=_xlfn.IFS($C33<$D$14,O$14, $C33<$D$15,O$15, $C33<$D$16,O$16)} -> 0.05 | P33: {=_xlfn.IFS($C33<$D$14,P$14, $C33<$D$15,P$15, $C33<$D$16,P$16)} -> 0.04 | Q33: {=_xlfn.IFS($C33<$D$14,Q$14, $C33<$D$15,Q$15, $C33<$D$16,Q$16)} -> 0.08 | R33: {=_xlfn.IFS($C33<$D$14,R$14, $C33<$D$15,R$15, $C33<$D$16,R$16)} -> 0.06 | S33: {=_xlfn.IFS($C33<$D$14,S$14, $C33<$D$15,S$15, $C33<$D$16,S$16)} -> 0.04 | T33: {=_xlfn.IFS($C33<$D$14,T$14, $C33<$D$15,T$15, $C33<$D$16,T$16)} -> 0.05 | U33: {=_xlfn.IFS($C33<$D$14,U$14, $C33<$D$15,U$15, $C33<$D$16,U$16)} -> 0 | V33: {=_xlfn.IFS($C33<$D$14,V$14, $C33<$D$15,V$15, $C33<$D$16,V$16)} -> 10000 | AA33: {=_xlfn.IFS($C33<$Z$14,AA$14, $C33<$Z$15,AA$15, $C33<$Z$16,AA$16)} -> 0.14 | AB33: {=_xlfn.IFS($C33<$Z$14,AB$14, $C33<$Z$15,AB$15, $C33<$Z$16,AB$16)} -> 0.16 | AC33: {=_xlfn.IFS($C33<$Z$14,AC$14, $C33<$Z$15,AC$15, $C33<$Z$16,AC$16)} -> 0.2 | AD33: {=_xlfn.IFS($C33<$Z$14,AD$14, $C33<$Z$15,AD$15, $C33<$Z$16,AD$16)} -> 0.05 | AE33: {=_xlfn.IFS($C33<$Z$14,AE$14, $C33<$Z$15,AE$15, $C33<$Z$16,AE$16)} -> 0.03
... A55: 54 | B55: 0.35616888 | C55: =RAND() -> 0.62523235 | E55: {=_xlfn.IFS($C55<$D$14,E$14, $C55<$D$15,E$15, $C55<$D$16,E$16)} -> 0.1 | F55: {=_xlfn.IFS($C55<$D$14,F$14, $C55<$D$15,F$15, $C55<$D$16,F$16)} -> 0.05 | G55: {=_xlfn.IFS($C55<$D$14,G$14, $C55<$D$15,G$15, $C55<$D$16,G$16)} -> 0.05 | H55: {=_xlfn.IFS($C55<$D$14,H$14, $C55<$D$15,H$15, $C55<$D$16,H$16)} -> 0.1 | I55: {=_xlfn.IFS($C55<$D$14,I$14, $C55<$D$15,I$15, $C55<$D$16,I$16)} -> 0 | O55: {=_xlfn.IFS($C55<$D$14,O$14, $C55<$D$15,O$15, $C55<$D$16,O$16)} -> 0.05 | P55: {=_xlfn.IFS($C55<$D$14,P$14, $C55<$D$15,P$15, $C55<$D$16,P$16)} -> 0.04 | Q55: {=_xlfn.IFS($C55<$D$14,Q$14, $C55<$D$15,Q$15, $C55<$D$16,Q$16)} -> 0.08 | R55: {=_xlfn.IFS($C55<$D$14,R$14, $C55<$D$15,R$15, $C55<$D$16,R$16)} -> 0.06 | S55: {=_xlfn.IFS($C55<$D$14,S$14, $C55<$D$15,S$15, $C55<$D$16,S$16)} -> 0.04 | T55: {=_xlfn.IFS($C55<$D$14,T$14, $C55<$D$15,T$15, $C55<$D$16,T$16)} -> 0.05 | U55: {=_xlfn.IFS($C55<$D$14,U$14, $C55<$D$15,U$15, $C55<$D$16,U$16)} -> 0 | V55: {=_xlfn.IFS($C55<$D$14,V$14, $C55<$D$15,V$15, $C55<$D$16,V$16)} -> 10000 | AA55: {=_xlfn.IFS($C55<$Z$14,AA$14, $C55<$Z$15,AA$15, $C55<$Z$16,AA$16)} -> 0.14 | AB55: {=_xlfn.IFS($C55<$Z$14,AB$14, $C55<$Z$15,AB$15, $C55<$Z$16,AB$16)} -> 0.16 | AC55: {=_xlfn.IFS($C55<$Z$14,AC$14, $C55<$Z$15,AC$15, $C55<$Z$16,AC$16)} -> 0.2 | AD55: {=_xlfn.IFS($C55<$Z$14,AD$14, $C55<$Z$15,AD$15, $C55<$Z$16,AD$16)} -> 0.05 | AE55: {=_xlfn.IFS($C55<$Z$14,AE$14, $C55<$Z$15,AE$15, $C55<$Z$16,AE$16)} -> 0.03
B56: 0.65810393 | C56: =RAND() -> 0.60688739 | E56: {=_xlfn.IFS($C56<$D$14,E$14, $C56<$D$15,E$15, $C56<$D$16,E$16)} -> 0.1 | F56: {=_xlfn.IFS($C56<$D$14,F$14, $C56<$D$15,F$15, $C56<$D$16,F$16)} -> 0.05 | G56: {=_xlfn.IFS($C56<$D$14,G$14, $C56<$D$15,G$15, $C56<$D$16,G$16)} -> 0.05 | H56: {=_xlfn.IFS($C56<$D$14,H$14, $C56<$D$15,H$15, $C56<$D$16,H$16)} -> 0.1 | I56: {=_xlfn.IFS($C56<$D$14,I$14, $C56<$D$15,I$15, $C56<$D$16,I$16)} -> 0 | O56: {=_xlfn.IFS($C56<$D$14,O$14, $C56<$D$15,O$15, $C56<$D$16,O$16)} -> 0.05 | P56: {=_xlfn.IFS($C56<$D$14,P$14, $C56<$D$15,P$15, $C56<$D$16,P$16)} -> 0.04 | Q56: {=_xlfn.IFS($C56<$D$14,Q$14, $C56<$D$15,Q$15, $C56<$D$16,Q$16)} -> 0.08 | R56: {=_xlfn.IFS($C56<$D$14,R$14, $C56<$D$15,R$15, $C56<$D$16,R$16)} -> 0.06 | S56: {=_xlfn.IFS($C56<$D$14,S$14, $C56<$D$15,S$15, $C56<$D$16,S$16)} -> 0.04 | T56: {=_xlfn.IFS($C56<$D$14,T$14, $C56<$D$15,T$15, $C56<$D$16,T$16)} -> 0.05 | U56: {=_xlfn.IFS($C56<$D$14,U$14, $C56<$D$15,U$15, $C56<$D$16,U$16)} -> 0 | V56: {=_xlfn.IFS($C56<$D$14,V$14, $C56<$D$15,V$15, $C56<$D$16,V$16)} -> 10000 | AA56: {=_xlfn.IFS($C56<$Z$14,AA$14, $C56<$Z$15,AA$15, $C56<$Z$16,AA$16)} -> 0.14 | AB56: {=_xlfn.IFS($C56<$Z$14,AB$14, $C56<$Z$15,AB$15, $C56<$Z$16,AB$16)} -> 0.16 | AC56: {=_xlfn.IFS($C56<$Z$14,AC$14, $C56<$Z$15,AC$15, $C56<$Z$16,AC$16)} -> 0.2 | AD56: {=_xlfn.IFS($C56<$Z$14,AD$14, $C56<$Z$15,AD$15, $C56<$Z$16,AD$16)} -> 0.05 | AE56: {=_xlfn.IFS($C56<$Z$14,AE$14, $C56<$Z$15,AE$15, $C56<$Z$16,AE$16)} -> 0.03
B57: 0.63244219 | C57: =RAND() -> 0.21347119 | E57: {=_xlfn.IFS($C57<$D$14,E$14, $C57<$D$15,E$15, $C57<$D$16,E$16)} -> 0.1 | F57: {=_xlfn.IFS($C57<$D$14,F$14, $C57<$D$15,F$15, $C57<$D$16,F$16)} -> 0.05 | G57: {=_xlfn.IFS($C57<$D$14,G$14, $C57<$D$15,G$15, $C57<$D$16,G$16)} -> 0.05 | H57: {=_xlfn.IFS($C57<$D$14,H$14, $C57<$D$15,H$15, $C57<$D$16,H$16)} -> 0.1 | I57: {=_xlfn.IFS($C57<$D$14,I$14, $C57<$D$15,I$15, $C57<$D$16,I$16)} -> 0 | O57: {=_xlfn.IFS($C57<$D$14,O$14, $C57<$D$15,O$15, $C57<$D$16,O$16)} -> 0.05 | P57: {=_xlfn.IFS($C57<$D$14,P$14, $C57<$D$15,P$15, $C57<$D$16,P$16)} -> 0.04 | Q57: {=_xlfn.IFS($C57<$D$14,Q$14, $C57<$D$15,Q$15, $C57<$D$16,Q$16)} -> 0.08 | R57: {=_xlfn.IFS($C57<$D$14,R$14, $C57<$D$15,R$15, $C57<$D$16,R$16)} -> 0.06 | S57: {=_xlfn.IFS($C57<$D$14,S$14, $C57<$D$15,S$15, $C57<$D$16,S$16)} -> 0.04 | T57: {=_xlfn.IFS($C57<$D$14,T$14, $C57<$D$15,T$15, $C57<$D$16,T$16)} -> 0.05 | U57: {=_xlfn.IFS($C57<$D$14,U$14, $C57<$D$15,U$15, $C57<$D$16,U$16)} -> 0 | V57: {=_xlfn.IFS($C57<$D$14,V$14, $C57<$D$15,V$15, $C57<$D$16,V$16)} -> 10000 | AA57: {=_xlfn.IFS($C57<$Z$14,AA$14, $C57<$Z$15,AA$15, $C57<$Z$16,AA$16)} -> 0.14 | AB57: {=_xlfn.IFS($C57<$Z$14,AB$14, $C57<$Z$15,AB$15, $C57<$Z$16,AB$16)} -> 0.16 | AC57: {=_xlfn.IFS($C57<$Z$14,AC$14, $C57<$Z$15,AC$15, $C57<$Z$16,AC$16)} -> 0.2 | AD57: {=_xlfn.IFS($C57<$Z$14,AD$14, $C57<$Z$15,AD$15, $C57<$Z$16,AD$16)} -> 0.05 | AE57: {=_xlfn.IFS($C57<$Z$14,AE$14, $C57<$Z$15,AE$15, $C57<$Z$16,AE$16)} -> 0.03
B58: 0.098462824 | C58: =RAND() -> 0.27180056 | E58: {=_xlfn.IFS($C58<$D$14,E$14, $C58<$D$15,E$15, $C58<$D$16,E$16)} -> 0.1 | F58: {=_xlfn.IFS($C58<$D$14,F$14, $C58<$D$15,F$15, $C58<$D$16,F$16)} -> 0.05 | G58: {=_xlfn.IFS($C58<$D$14,G$14, $C58<$D$15,G$15, $C58<$D$16,G$16)} -> 0.05 | H58: {=_xlfn.IFS($C58<$D$14,H$14, $C58<$D$15,H$15, $C58<$D$16,H$16)} -> 0.1 | I58: {=_xlfn.IFS($C58<$D$14,I$14, $C58<$D$15,I$15, $C58<$D$16,I$16)} -> 0 | O58: {=_xlfn.IFS($C58<$D$14,O$14, $C58<$D$15,O$15, $C58<$D$16,O$16)} -> 0.05 | P58: {=_xlfn.IFS($C58<$D$14,P$14, $C58<$D$15,P$15, $C58<$D$16,P$16)} -> 0.04 | Q58: {=_xlfn.IFS($C58<$D$14,Q$14, $C58<$D$15,Q$15, $C58<$D$16,Q$16)} -> 0.08 | R58: {=_xlfn.IFS($C58<$D$14,R$14, $C58<$D$15,R$15, $C58<$D$16,R$16)} -> 0.06 | S58: {=_xlfn.IFS($C58<$D$14,S$14, $C58<$D$15,S$15, $C58<$D$16,S$16)} -> 0.04 | T58: {=_xlfn.IFS($C58<$D$14,T$14, $C58<$D$15,T$15, $C58<$D$16,T$16)} -> 0.05 | U58: {=_xlfn.IFS($C58<$D$14,U$14, $C58<$D$15,U$15, $C58<$D$16,U$16)} -> 0 | V58: {=_xlfn.IFS($C58<$D$14,V$14, $C58<$D$15,V$15, $C58<$D$16,V$16)} -> 10000 | AA58: {=_xlfn.IFS($C58<$Z$14,AA$14, $C58<$Z$15,AA$15, $C58<$Z$16,AA$16)} -> 0.14 | AB58: {=_xlfn.IFS($C58<$Z$14,AB$14, $C58<$Z$15,AB$15, $C58<$Z$16,AB$16)} -> 0.16 | AC58: {=_xlfn.IFS($C58<$Z$14,AC$14, $C58<$Z$15,AC$15, $C58<$Z$16,AC$16)} -> 0.2 | AD58: {=_xlfn.IFS($C58<$Z$14,AD$14, $C58<$Z$15,AD$15, $C58<$Z$16,AD$16)} -> 0.05 | AE58: {=_xlfn.IFS($C58<$Z$14,AE$14, $C58<$Z$15,AE$15, $C58<$Z$16,AE$16)} -> 0.03
B59: 0.25654279 | C59: =RAND() -> 0.34044587 | E59: {=_xlfn.IFS($C59<$D$14,E$14, $C59<$D$15,E$15, $C59<$D$16,E$16)} -> 0.1 | F59: {=_xlfn.IFS($C59<$D$14,F$14, $C59<$D$15,F$15, $C59<$D$16,F$16)} -> 0.05 | G59: {=_xlfn.IFS($C59<$D$14,G$14, $C59<$D$15,G$15, $C59<$D$16,G$16)} -> 0.05 | H59: {=_xlfn.IFS($C59<$D$14,H$14, $C59<$D$15,H$15, $C59<$D$16,H$16)} -> 0.1 | I59: {=_xlfn.IFS($C59<$D$14,I$14, $C59<$D$15,I$15, $C59<$D$16,I$16)} -> 0 | O59: {=_xlfn.IFS($C59<$D$14,O$14, $C59<$D$15,O$15, $C59<$D$16,O$16)} -> 0.05 | P59: {=_xlfn.IFS($C59<$D$14,P$14, $C59<$D$15,P$15, $C59<$D$16,P$16)} -> 0.04 | Q59: {=_xlfn.IFS($C59<$D$14,Q$14, $C59<$D$15,Q$15, $C59<$D$16,Q$16)} -> 0.08 | R59: {=_xlfn.IFS($C59<$D$14,R$14, $C59<$D$15,R$15, $C59<$D$16,R$16)} -> 0.06 | S59: {=_xlfn.IFS($C59<$D$14,S$14, $C59<$D$15,S$15, $C59<$D$16,S$16)} -> 0.04 | T59: {=_xlfn.IFS($C59<$D$14,T$14, $C59<$D$15,T$15, $C59<$D$16,T$16)} -> 0.05 | U59: {=_xlfn.IFS($C59<$D$14,U$14, $C59<$D$15,U$15, $C59<$D$16,U$16)} -> 0 | V59: {=_xlfn.IFS($C59<$D$14,V$14, $C59<$D$15,V$15, $C59<$D$16,V$16)} -> 10000 | AA59: {=_xlfn.IFS($C59<$Z$14,AA$14, $C59<$Z$15,AA$15, $C59<$Z$16,AA$16)} -> 0.14 | AB59: {=_xlfn.IFS($C59<$Z$14,AB$14, $C59<$Z$15,AB$15, $C59<$Z$16,AB$16)} -> 0.16 | AC59: {=_xlfn.IFS($C59<$Z$14,AC$14, $C59<$Z$15,AC$15, $C59<$Z$16,AC$16)} -> 0.2 | AD59: {=_xlfn.IFS($C59<$Z$14,AD$14, $C59<$Z$15,AD$15, $C59<$Z$16,AD$16)} -> 0.05 | AE59: {=_xlfn.IFS($C59<$Z$14,AE$14, $C59<$Z$15,AE$15, $C59<$Z$16,AE$16)} -> 0.03
B60: 0.84716646 | C60: =RAND() -> 0.53360359 | E60: {=_xlfn.IFS($C60<$D$14,E$14, $C60<$D$15,E$15, $C60<$D$16,E$16)} -> 0.1 | F60: {=_xlfn.IFS($C60<$D$14,F$14, $C60<$D$15,F$15, $C60<$D$16,F$16)} -> 0.05 | G60: {=_xlfn.IFS($C60<$D$14,G$14, $C60<$D$15,G$15, $C60<$D$16,G$16)} -> 0.05 | H60: {=_xlfn.IFS($C60<$D$14,H$14, $C60<$D$15,H$15, $C60<$D$16,H$16)} -> 0.1 | I60: {=_xlfn.IFS($C60<$D$14,I$14, $C60<$D$15,I$15, $C60<$D$16,I$16)} -> 0 | O60: {=_xlfn.IFS($C60<$D$14,O$14, $C60<$D$15,O$15, $C60<$D$16,O$16)} -> 0.05 | P60: {=_xlfn.IFS($C60<$D$14,P$14, $C60<$D$15,P$15, $C60<$D$16,P$16)} -> 0.04 | Q60: {=_xlfn.IFS($C60<$D$14,Q$14, $C60<$D$15,Q$15, $C60<$D$16,Q$16)} -> 0.08 | R60: {=_xlfn.IFS($C60<$D$14,R$14, $C60<$D$15,R$15, $C60<$D$16,R$16)} -> 0.06 | S60: {=_xlfn.IFS($C60<$D$14,S$14, $C60<$D$15,S$15, $C60<$D$16,S$16)} -> 0.04 | T60: {=_xlfn.IFS($C60<$D$14,T$14, $C60<$D$15,T$15, $C60<$D$16,T$16)} -> 0.05 | U60: {=_xlfn.IFS($C60<$D$14,U$14, $C60<$D$15,U$15, $C60<$D$16,U$16)} -> 0 | V60: {=_xlfn.IFS($C60<$D$14,V$14, $C60<$D$15,V$15, $C60<$D$16,V$16)} -> 10000 | AA60: {=_xlfn.IFS($C60<$Z$14,AA$14, $C60<$Z$15,AA$15, $C60<$Z$16,AA$16)} -> 0.14 | AB60: {=_xlfn.IFS($C60<$Z$14,AB$14, $C60<$Z$15,AB$15, $C60<$Z$16,AB$16)} -> 0.16 | AC60: {=_xlfn.IFS($C60<$Z$14,AC$14, $C60<$Z$15,AC$15, $C60<$Z$16,AC$16)} -> 0.2 | AD60: {=_xlfn.IFS($C60<$Z$14,AD$14, $C60<$Z$15,AD$15, $C60<$Z$16,AD$16)} -> 0.05 | AE60: {=_xlfn.IFS($C60<$Z$14,AE$14, $C60<$Z$15,AE$15, $C60<$Z$16,AE$16)} -> 0.03

Sheet Calc Engine
BE2: Deviations allowed | BF2: 0.1
BE3: % Of Goals Met | BF3: =COUNTIF(#REF!,"Goal Met")/COUNTA('Calc Engine'!$AL$8:$AL$17) -> #REF!
AM4: 1 - being least imp
E5: Goal | AP5: In Rs - Goal Value | BG5: Total Surplus | BH5: =SUM(Sum_Of_Wt_Adj_Surplus[Total]) -> -9481062.8
AP6: Source
AL7: Goal | AM7: Goal Importance | AN7: At Age | AP7: Large Cap | AQ7: Goal Met ? | AR7: Value At Age | AS7: Surplus | AT7: Wt_Adjusted_Surplus | AV7: Mid Cap | AW7: Goal Met ? | AX7: Value At Age | AY7: Surplus | AZ7: Wt_Adjusted_Surplus | BB7: Small Cap | BC7: Goal Met ? | BD7: Value At Age | BE7: Surplus | BF7: Wt_Adjusted_Surplus | BH7: Column1 | BI7: Total | BJ7: Goal Met ?
AL8: {=[1]!Goal_Input[Goal]} -> Own Health Fund | AM8: {=[1]!Goal_Input[Goal Importance]} -> 1 | AN8: {=[1]!Goal_Input[[At Age ]]} -> 32 | AP8: =[1]Details!M14 -> 660000 | AQ8: =IFERROR(IF(ISBLANK('Calc Engine'!$AL8),"No Goal",('Calc Engine'!$AP8*(1-$BF$2))<=_xlfn.XLOOKUP('Calc Engine'!$AN8,Age,End_Of_Year_Value_Large_Cap)),"-") -> FALSE | AR8: =IF('Calc Engine'!$AP8> 0,_xlfn.XLOOKUP(AN8,Age,End_Of_Year_Value_Large_Cap),0) -> 221864.68 | AS8: ='Calc Engine'!$AR8-'Calc Engine'!$AP8 -> -438135.32 | AT8: =PRODUCT('Calc Engine'!$AS8,'Calc Engine'!$AM8) -> -438135.32 | AV8: =[1]Details!N14 -> 0 | AW8: =IFERROR(IF(ISBLANK('Calc Engine'!$AL8),"No Goal",('Calc Engine'!$AV8*(1-$BF$2))<=_xlfn.XLOOKUP('Calc Engine'!$AN8,Age,End_Of_Year_Value_Mid_Cap)),"-") -> FALSE | AX8: =IF(Mid_Cap_Goal[[#This Row],[Mid Cap]]>0,_xlfn.XLOOKUP(AN8,Age,End_Of_Year_Value_Mid_Cap),0) -> 0 | AY8: ='Calc Engine'!$AX8-'Calc Engine'!$AV8 -> 0 | AZ8: =PRODUCT('Calc Engine'!$AY8,'Calc Engine'!$AM8) -> 0 | BB8: =[1]Details!O14 -> 0 | BC8: =IFERROR(IF(ISBLANK('Calc Engine'!$AL8),"No Goal",('Calc Engine'!$BB8 * (1 -$BF$2))<=_xlfn.XLOOKUP('Calc Engine'!$AN8,Age,End_Of_Year_Value_Small_Cap)),"-") -> TRUE | BD8: =IF(Small_Cap_Goal[[#This Row],[Small Cap]],_xlfn.XLOOKUP(AN8,Age,End_Of_Year_Value_Small_Cap),0) -> 0 | BE8: ='Calc Engine'!$BD8-'Calc Engine'!$BB8 -> 0 | BF8: =PRODUCT('Calc Engine'!$BE8,'Calc Engine'!$AM8) -> 0 | BH8: =AL8 -> Own Health Fund | BI8: =SUM(Small_Cap_Goal[[#This Row],[Wt_Adjusted_Surplus]],Mid_Cap_Goal[[#This Row],[Wt_Adjusted_Surplus]],Large_Cap_Goal[[#This Row],[Wt_Adjusted_Surplus]]) -> -438135.32 | BJ8: =Sum_Of_Wt_Adj_Surplus[[#This Row],[Total]]>0 -> FALSE
AL9: Marriage | AM9: 1 | AN9: 35 | AP9: =[1]Details!M15 -> 0 | AQ9: =IFERROR(IF(ISBLANK('Calc Engine'!$AL9),"No Goal",('Calc Engine'!$AP9*(1-$BF$2))<=_xlfn.XLOOKUP('Calc Engine'!$AN9,Age,End_Of_Year_Value_Large_Cap)),"-") -> FALSE | AR9: =IF('Calc Engine'!$AP9> 0,_xlfn.XLOOKUP(AN9,Age,End_Of_Year_Value_Large_Cap),0) -> 0 | AS9: ='Calc Engine'!$AR9-'Calc Engine'!$AP9 -> 0 | AT9: =PRODUCT('Calc Engine'!$AS9,'Calc Engine'!$AM9) -> 0 | AV9: =[1]Details!N15 -> 340000 | AW9: =IFERROR(IF(ISBLANK('Calc Engine'!$AL9),"No Goal",('Calc Engine'!$AV9*(1-$BF$2))<=_xlfn.XLOOKUP('Calc Engine'!$AN9,Age,End_Of_Year_Value_Mid_Cap)),"-") -> FALSE | AX9: =IF(Mid_Cap_Goal[[#This Row],[Mid Cap]]>0,_xlfn.XLOOKUP(AN9,Age,End_Of_Year_Value_Mid_Cap),0) -> -117195.6 | AY9: ='Calc Engine'!$AX9-'Calc Engine'!$AV9 -> -457195.6 | AZ9: =PRODUCT('Calc Engine'!$AY9,'Calc Engine'!$AM9) -> -457195.6 | BB9: =[1]Details!O15 -> 0 | BC9: =IFERROR(IF(ISBLANK('Calc Engine'!$AL9),"No Goal",('Calc Engine'!$BB9 * (1 -$BF$2))<=_xlfn.XLOOKUP('Calc Engine'!$AN9,Age,End_Of_Year_Value_Small_Cap)),"-") -> TRUE | BD9: =IF(Small_Cap_Goal[[#This Row],[Small Cap]],_xlfn.XLOOKUP(AN9,Age,End_Of_Year_Value_Small_Cap),0) -> 0 | BE9: ='Calc Engine'!$BD9-'Calc Engine'!$BB9 -> 0 | BF9: =PRODUCT('Calc Engine'!$BE9,'Calc Engine'!$AM9) -> 0 | BH9: =AL9 -> Marriage | BI9: =SUM(Small_Cap_Goal[[#This Row],[Wt_Adjusted_Surplus]],Mid_Cap_Goal[[#This Row],[Wt_Adjusted_Surplus]],Large_Cap_Goal[[#This Row],[Wt_Adjusted_Surplus]]) -> -457195.6 | BJ9: =Sum_Of_Wt_Adj_Surplus[[#This Row],[Total]]>0 -> FALSE
AL10: Children Education | AM10: 1 | AN10: 42 | AP10: =[1]Details!M16 -> 430000 | AQ10: =IFERROR(IF(ISBLANK('Calc Engine'!$AL10),"No Goal",('Calc Engine'!$AP10*(1-$BF$2))<=_xlfn.XLOOKUP('Calc Engine'!$AN10,Age,End_Of_Year_Value_Large_Cap)),"-") -> FALSE | AR10: =IF('Calc Engine'!$AP10> 0,_xlfn.XLOOKUP(AN10,Age,End_Of_Year_Value_Large_Cap),0) -> -1076850.7 | AS10: ='Calc Engine'!$AR10-'Calc Engine'!$AP10 -> -1506850.7 | AT10: =PRODUCT('Calc Engine'!$AS10,'Calc Engine'!$AM10) -> -1506850.7 | AV10: =[1]Details!N16 -> 0 | AW10: =IFERROR(IF(ISBLANK('Calc Engine'!$AL10),"No Goal",('Calc Engine'!$AV10*(1-$BF$2))<=_xlfn.XLOOKUP('Calc Engine'!$AN10,Age,End_Of_Year_Value_Mid_Cap)),"-") -> FALSE | AX10: =IF(Mid_Cap_Goal[[#This Row],[Mid Cap]]>0,_xlfn.XLOOKUP(AN10,Age,End_Of_Year_Value_Mid_Cap),0) -> 0 | AY10: ='Calc Engine'!$AX10-'Calc Engine'!$AV10 -> 0 | AZ10: =PRODUCT('Calc Engine'!$AY10,'Calc Engine'!$AM10) -> 0 | BB10: =[1]Details!O16 -> 0 | BC10: =IFERROR(IF(ISBLANK('Calc Engine'!$AL10),"No Goal",('Calc Engine'!$BB10 * (1 -$BF$2))<=_xlfn.XLOOKUP('Calc Engine'!$AN10,Age,End_Of_Year_Value_Small_Cap)),"-") -> TRUE | BD10: =IF(Small_Cap_Goal[[#This Row],[Small Cap]],_xlfn.XLOOKUP(AN10,Age,End_Of_Year_Value_Small_Cap),0) -> 0 | BE10: ='Calc Engine'!$BD10-'Calc Engine'!$BB10 -> 0 | BF10: =PRODUCT('Calc Engine'!$BE10,'Calc Engine'!$AM10) -> 0 | BH10: =AL10 -> Children Education | BI10: =SUM(Small_Cap_Goal[[#This Row],[Wt_Adjusted_Surplus]],Mid_Cap_Goal[[#This Row],[Wt_Adjusted_Surplus]],Large_Cap_Goal[[#This Row],[Wt_Adjusted_Surplus]]) -> -1506850.7 | BJ10: =Sum_Of_Wt_Adj_Surplus[[#This Row],[Total]]>0 -> FALSE
AL11: House | AM11: 1 | AN11: 52 | AP11: =[1]Details!M17 -> 6000000 | AQ11: =IFERROR(IF(ISBLANK('Calc Engine'!$AL11),"No Goal",('Calc Engine'!$AP11*(1-$BF$2))<=_xlfn.XLOOKUP('Calc Engine'!$AN11,Age,End_Of_Year_Value_Large_Cap)),"-") -> FALSE | AR11: =IF('Calc Engine'!$AP11> 0,_xlfn.XLOOKUP(AN11,Age,End_Of_Year_Value_Large_Cap),0) -> -4067740.7 | AS11: ='Calc Engine'!$AR11-'Calc Engine'!$AP11 -> -10067741 | AT11: =PRODUCT('Calc Engine'!$AS11,'Calc Engine'!$AM11) -> -10067741 | AV11: =[1]Details!N17 -> 0 | AW11: =IFERROR(IF(ISBLANK('Calc Engine'!$AL11),"No Goal",('Calc Engine'!$AV11*(1-$BF$2))<=_xlfn.XLOOKUP('Calc Engine'!$AN11,Age,End_Of_Year_Value_Mid_Cap)),"-") -> FALSE | AX11: =IF(Mid_Cap_Goal[[#This Row],[Mid Cap]]>0,_xlfn.XLOOKUP(AN11,Age,End_Of_Year_Value_Mid_Cap),0) -> 0 | AY11: ='Calc Engine'!$AX11-'Calc Engine'!$AV11 -> 0 | AZ11: =PRODUCT('Calc Engine'!$AY11,'Calc Engine'!$AM11) -> 0 | BB11: =[1]Details!O17 -> 0 | BC11: =IFERROR(IF(ISBLANK('Calc Engine'!$AL11),"No Goal",('Calc Engine'!$BB11 * (1 -$BF$2))<=_xlfn.XLOOKUP('Calc Engine'!$AN11,Age,End_Of_Year_Value_Small_Cap)),"-") -> TRUE | BD11: =IF(Small_Cap_Goal[[#This Row],[Small Cap]],_xlfn.XLOOKUP(AN11,Age,End_Of_Year_Value_Small_Cap),0) -> 0 | BE11: ='Calc Engine'!$BD11-'Calc Engine'!$BB11 -> 0 | BF11: =PRODUCT('Calc Engine'!$BE11,'Calc Engine'!$AM11) -> 0 | BH11: =AL11 -> House | BI11: =SUM(Small_Cap_Goal[[#This Row],[Wt_Adjusted_Surplus]],Mid_Cap_Goal[[#This Row],[Wt_Adjusted_Surplus]],Large_Cap_Goal[[#This Row],[Wt_Adjusted_Surplus]]) -> -10067741 | BJ11: =Sum_Of_Wt_Adj_Surplus[[#This Row],[Total]]>0 -> FALSE
AL12: Car | AM12: 1 | AN12: 28 | AP12: =[1]Details!M18 -> 0 | AQ12: =IFERROR(IF(ISBLANK('Calc Engine'!$AL12),"No Goal",('Calc Engine'!$AP12*(1-$BF$2))<=_xlfn.XLOOKUP('Calc Engine'!$AN12,Age,End_Of_Year_Value_Large_Cap)),"-") -> TRUE | AR12: =IF('Calc Engine'!$AP12> 0,_xlfn.XLOOKUP(AN12,Age,End_Of_Year_Value_Large_Cap),0) -> 0 | AS12: ='Calc Engine'!$AR12-'Calc Engine'!$AP12 -> 0 | AT12: =PRODUCT('Calc Engine'!$AS12,'Calc Engine'!$AM12) -> 0 | AV12: =[1]Details!N18 -> 209000 | AW12: =IFERROR(IF(ISBLANK('Calc Engine'!$AL12),"No Goal",('Calc Engine'!$AV12*(1-$BF$2))<=_xlfn.XLOOKUP('Calc Engine'!$AN12,Age,End_Of_Year_Value_Mid_Cap)),"-") -> FALSE | AX12: =IF(Mid_Cap_Goal[[#This Row],[Mid Cap]]>0,_xlfn.XLOOKUP(AN12,Age,End_Of_Year_Value_Mid_Cap),0) -> 107761.62 | AY12: ='Calc Engine'!$AX12-'Calc Engine'!$AV12 -> -101238.38 | AZ12: =PRODUCT('Calc Engine'!$AY12,'Calc Engine'!$AM12) -> -101238.38 | BB12: =[1]Details!O18 -> 0 | BC12: =IFERROR(IF(ISBLANK('Calc Engine'!$AL12),"No Goal",('Calc Engine'!$BB12 * (1 -$BF$2))<=_xlfn.XLOOKUP('Calc Engine'!$AN12,Age,End_Of_Year_Value_Small_Cap)),"-") -> TRUE | BD12: =IF(Small_Cap_Goal[[#This Row],[Small Cap]],_xlfn.XLOOKUP(AN12,Age,End_Of_Year_Value_Small_Cap),0) -> 0 | BE12: ='Calc Engine'!$BD12-'Calc Engine'!$BB12 -> 0 | BF12: =PRODUCT('Calc Engine'!$BE12,'Calc Engine'!$AM12) -> 0 | BH12: =AL12 -> Car | BI12: =SUM(Small_Cap_Goal[[#This Row],[Wt_Adjusted_Surplus]],Mid_Cap_Goal[[#This Row],[Wt_Adjusted_Surplus]],Large_Cap_Goal[[#This Row],[Wt_Adjusted_Surplus]]) -> -101238.38 | BJ12: =Sum_Of_Wt_Adj_Surplus[[#This Row],[Total]]>0 -> FALSE
AL13: Abroad Vacation | AM13: 1 | AN13: 38 | AP13: =[1]Details!M19 -> 0 | AQ13: =IFERROR(IF(ISBLANK('Calc Engine'!$AL13),"No Goal",('Calc Engine'!$AP13*(1-$BF$2))<=_xlfn.XLOOKUP('Calc Engine'!$AN13,Age,End_Of_Year_Value_Large_Cap)),"-") -> FALSE | AR13: =IF('Calc Engine'!$AP13> 0,_xlfn.XLOOKUP(AN13,Age,End_Of_Year_Value_Large_Cap),0) -> 0 | AS13: ='Calc Engine'!$AR13-'Calc Engine'!$AP13 -> 0 | AT13: =PRODUCT('Calc Engine'!$AS13,'Calc Engine'!$AM13) -> 0 | AV13: =[1]Details!N19 -> 0 | AW13: =IFERROR(IF(ISBLANK('Calc Engine'!$AL13),"No Goal",('Calc Engine'!$AV13*(1-$BF$2))<=_xlfn.XLOOKUP('Calc Engine'!$AN13,Age,End_Of_Year_Value_Mid_Cap)),"-") -> FALSE | AX13: =IF(Mid_Cap_Goal[[#This Row],[Mid Cap]]>0,_xlfn.XLOOKUP(AN13,Age,End_Of_Year_Value_Mid_Cap),0) -> 0 | AY13: ='Calc Engine'!$AX13-'Calc Engine'!$AV13 -> 0 | AZ13: =PRODUCT('Calc Engine'!$AY13,'Calc Engine'!$AM13) -> 0 | BB13: =[1]Details!O19 -> 5500000 | BC13: =IFERROR(IF(ISBLANK('Calc Engine'!$AL13),"No Goal",('Calc Engine'!$BB13 * (1 -$BF$2))<=_xlfn.XLOOKUP('Calc Engine'!$AN13,Age,End_Of_Year_Value_Small_Cap)),"-") -> TRUE | BD13: =IF(Small_Cap_Goal[[#This Row],[Small Cap]],_xlfn.XLOOKUP(AN13,Age,End_Of_Year_Value_Small_Cap),0) -> 8590097.9 | BE13: ='Calc Engine'!$BD13-'Calc Engine'!$BB13 -> 3090097.9 | BF13: =PRODUCT('Calc Engine'!$BE13,'Calc Engine'!$AM13) -> 3090097.9 | BH13: =AL13 -> Abroad Vacation | BI13: =SUM(Small_Cap_Goal[[#This Row],[Wt_Adjusted_Surplus]],Mid_Cap_Goal[[#This Row],[Wt_Adjusted_Surplus]],Large_Cap_Goal[[#This Row],[Wt_Adjusted_Surplus]]) -> 3090097.9 | BJ13: =Sum_Of_Wt_Adj_Surplus[[#This Row],[Total]]>0 -> TRUE
AL14: 0 | AM14: 1 | AN14: 0 | AP14: =[1]Details!M20 -> 0 | AQ14: =IFERROR(IF(ISBLANK('Calc Engine'!$AL14),"No Goal",('Calc Engine'!$AP14*(1-$BF$2))<=_xlfn.XLOOKUP('Calc Engine'!$AN14,Age,End_Of_Year_Value_Large_Cap)),"-") -> - | AR14: =IF('Calc Engine'!$AP14> 0,_xlfn.XLOOKUP(AN14,Age,End_Of_Year_Value_Large_Cap),0) -> 0 | AS14: ='Calc Engine'!$AR14-'Calc Engine'!$AP14 -> 0 | AT14: =PRODUCT('Calc Engine'!$AS14,'Calc Engine'!$AM14) -> 0 | AV14: =[1]Details!N20 -> 0 | AW14: =IFERROR(IF(ISBLANK('Calc Engine'!$AL14),"No Goal",('Calc Engine'!$AV14*(1-$BF$2))<=_xlfn.XLOOKUP('Calc Engine'!$AN14,Age,End_Of_Year_Value_Mid_Cap)),"-") -> - | AX14: =IF(Mid_Cap_Goal[[#This Row],[Mid Cap]]>0,_xlfn.XLOOKUP(AN14,Age,End_Of_Year_Value_Mid_Cap),0) -> 0 | AY14: ='Calc Engine'!$AX14-'Calc Engine'!$AV14 -> 0 | AZ14: =PRODUCT('Calc Engine'!$AY14,'Calc Engine'!$AM14) -> 0 | BB14: =[1]Details!O20 -> 0 | BC14: =IFERROR(IF(ISBLANK('Calc Engine'!$AL14),"No Goal",('Calc Engine'!$BB14 * (1 -$BF$2))<=_xlfn.XLOOKUP('Calc Engine'!$AN14,Age,End_Of_Year_Value_Small_Cap)),"-") -> - | BD14: =IF(Small_Cap_Goal[[#This Row],[Small Cap]],_xlfn.XLOOKUP(AN14,Age,End_Of_Year_Value_Small_Cap),0) -> 0 | BE14: ='Calc Engine'!$BD14-'Calc Engine'!$BB14 -> 0 | BF14: =PRODUCT('Calc Engine'!$BE14,'Calc Engine'!$AM14) -> 0 | BH14: =AL14 -> 0 | BI14: =SUM(Small_Cap_Goal[[#This Row],[Wt_Adjusted_Surplus]],Mid_Cap_Goal[[#This Row],[Wt_Adjusted_Surplus]],Large_Cap_Goal[[#This Row],[Wt_Adjusted_Surplus]]) -> 0 | BJ14: =Sum_Of_Wt_Adj_Surplus[[#This Row],[Total]]>0 -> FALSE
AL15: 0 | AM15: 1 | AN15: 0 | AP15: =[1]Details!M21 -> 0 | AQ15: =IFERROR(IF(ISBLANK('Calc Engine'!$AL15),"No Goal",('Calc Engine'!$AP15*(1-$BF$2))<=_xlfn.XLOOKUP('Calc Engine'!$AN15,Age,End_Of_Year_Value_Large_Cap)),"-") -> - | AR15: =IF('Calc Engine'!$AP15> 0,_xlfn.XLOOKUP(AN15,Age,End_Of_Year_Value_Large_Cap),0) -> 0 | AS15: ='Calc Engine'!$AR15-'Calc Engine'!$AP15 -> 0 | AT15: =PRODUCT('Calc Engine'!$AS15,'Calc Engine'!$AM15) -> 0 | AV15: =[1]Details!N21 -> 0 | AW15: =IFERROR(IF(ISBLANK('Calc Engine'!$AL15),"No Goal",('Calc Engine'!$AV15*(1-$BF$2))<=_xlfn.XLOOKUP('Calc Engine'!$AN15,Age,End_Of_Year_Value_Mid_Cap)),"-") -> - | AX15: =IF(Mid_Cap_Goal[[#This Row],[Mid Cap]]>0,_xlfn.XLOOKUP(AN15,Age,End_Of_Year_Value_Mid_Cap),0) -> 0 | AY15: ='Calc Engine'!$AX15-'Calc Engine'!$AV15 -> 0 | AZ15: =PRODUCT('Calc Engine'!$AY15,'Calc Engine'!$AM15) -> 0 | BB15: =[1]Details!O21 -> 0 | BC15: =IFERROR(IF(ISBLANK('Calc Engine'!$AL15),"No Goal",('Calc Engine'!$BB15 * (1 -$BF$2))<=_xlfn.XLOOKUP('Calc Engine'!$AN15,Age,End_Of_Year_Value_Small_Cap)),"-") -> - | BD15: =IF(Small_Cap_Goal[[#This Row],[Small Cap]],_xlfn.XLOOKUP(AN15,Age,End_Of_Year_Value_Small_Cap),0) -> 0 | BE15: ='Calc Engine'!$BD15-'Calc Engine'!$BB15 -> 0 | BF15: =PRODUCT('Calc Engine'!$BE15,'Calc Engine'!$AM15) -> 0 | BH15: =AL15 -> 0 | BI15: =SUM(Small_Cap_Goal[[#This Row],[Wt_Adjusted_Surplus]],Mid_Cap_Goal[[#This Row],[Wt_Adjusted_Surplus]],Large_Cap_Goal[[#This Row],[Wt_Adjusted_Surplus]]) -> 0 | BJ15: =Sum_Of_Wt_Adj_Surplus[[#This Row],[Total]]>0 -> FALSE
AL16: 0 | AM16: 1 | AN16: 0 | AP16: =[1]Details!M22 -> 0 | AQ16: =IFERROR(IF(ISBLANK('Calc Engine'!$AL16),"No Goal",('Calc Engine'!$AP16*(1-$BF$2))<=_xlfn.XLOOKUP('Calc Engine'!$AN16,Age,End_Of_Year_Value_Large_Cap)),"-") -> - | AR16: =IF('Calc Engine'!$AP16> 0,_xlfn.XLOOKUP(AN16,Age,End_Of_Year_Value_Large_Cap),0) -> 0 | AS16: ='Calc Engine'!$AR16-'Calc Engine'!$AP16 -> 0 | AT16: =PRODUCT('Calc Engine'!$AS16,'Calc Engine'!$AM16) -> 0 | AV16: =[1]Details!N22 -> 0 | AW16: =IFERROR(IF(ISBLANK('Calc Engine'!$AL16),"No Goal",('Calc Engine'!$AV16*(1-$BF$2))<=_xlfn.XLOOKUP('Calc Engine'!$AN16,Age,End_Of_Year_Value_Mid_Cap)),"-") -> - | AX16: =IF(Mid_Cap_Goal[[#This Row],[Mid Cap]]>0,_xlfn.XLOOKUP(AN16,Age,End_Of_Year_Value_Mid_Cap),0) -> 0 | AY16: ='Calc Engine'!$AX16-'Calc Engine'!$AV16 -> 0 | AZ16: =PRODUCT('Calc Engine'!$AY16,'Calc Engine'!$AM16) -> 0 | BB16: =[1]Details!O22 -> 0 | BC16: =IFERROR(IF(ISBLANK('Calc Engine'!$AL16),"No Goal",('Calc Engine'!$BB16 * (1 -$BF$2))<=_xlfn.XLOOKUP('Calc Engine'!$AN16,Age,End_Of_Year_Value_Small_Cap)),"-") -> - | BD16: =IF(Small_Cap_Goal[[#This Row],[Small Cap]],_xlfn.XLOOKUP(AN16,Age,End_Of_Year_Value_Small_Cap),0) -> 0 | BE16: ='Calc Engine'!$BD16-'Calc Engine'!$BB16 -> 0 | BF16: =PRODUCT('Calc Engine'!$BE16,'Calc Engine'!$AM16) -> 0 | BH16: =AL16 -> 0 | BI16: =SUM(Small_Cap_Goal[[#This Row],[Wt_Adjusted_Surplus]],Mid_Cap_Goal[[#This Row],[Wt_Adjusted_Surplus]],Large_Cap_Goal[[#This Row],[Wt_Adjusted_Surplus]]) -> 0 | BJ16: =Sum_Of_Wt_Adj_Surplus[[#This Row],[Total]]>0 -> FALSE
AL17: 0 | AM17: 1 | AN17: 0 | AP17: =[1]Details!M23 -> 0 | AQ17: =IFERROR(IF(ISBLANK('Calc Engine'!$AL17),"No Goal",('Calc Engine'!$AP17*(1-$BF$2))<=_xlfn.XLOOKUP('Calc Engine'!$AN17,Age,End_Of_Year_Value_Large_Cap)),"-") -> - | AR17: =IF('Calc Engine'!$AP17> 0,_xlfn.XLOOKUP(AN17,Age,End_Of_Year_Value_Large_Cap),0) -> 0 | AS17: ='Calc Engine'!$AR17-'Calc Engine'!$AP17 -> 0 | AT17: =PRODUCT('Calc Engine'!$AS17,'Calc Engine'!$AM17) -> 0 | AV17: =[1]Details!N23 -> 0 | AW17: =IFERROR(IF(ISBLANK('Calc Engine'!$AL17),"No Goal",('Calc Engine'!$AV17*(1-$BF$2))<=_xlfn.XLOOKUP('Calc Engine'!$AN17,Age,End_Of_Year_Value_Mid_Cap)),"-") -> - | AX17: =IF(Mid_Cap_Goal[[#This Row],[Mid Cap]]>0,_xlfn.XLOOKUP(AN17,Age,End_Of_Year_Value_Mid_Cap),0) -> 0 | AY17: ='Calc Engine'!$AX17-'Calc Engine'!$AV17 -> 0 | AZ17: =PRODUCT('Calc Engine'!$AY17,'Calc Engine'!$AM17) -> 0 | BB17: =[1]Details!O23 -> 0 | BC17: =IFERROR(IF(ISBLANK('Calc Engine'!$AL17),"No Goal",('Calc Engine'!$BB17 * (1 -$BF$2))<=_xlfn.XLOOKUP('Calc Engine'!$AN17,Age,End_Of_Year_Value_Small_Cap)),"-") -> - | BD17: =IF(Small_Cap_Goal[[#This Row],[Small Cap]],_xlfn.XLOOKUP(AN17,Age,End_Of_Year_Value_Small_Cap),0) -> 0 | BE17: ='Calc Engine'!$BD17-'Calc Engine'!$BB17 -> 0 | BF17: =PRODUCT('Calc Engine'!$BE17,'Calc Engine'!$AM17) -> 0 | BH17: =AL17 -> 0 | BI17: =SUM(Small_Cap_Goal[[#This Row],[Wt_Adjusted_Surplus]],Mid_Cap_Goal[[#This Row],[Wt_Adjusted_Surplus]],Large_Cap_Goal[[#This Row],[Wt_Adjusted_Surplus]]) -> 0 | BJ17: =Sum_Of_Wt_Adj_Surplus[[#This Row],[Total]]>0 -> FALSE
AL20: Amt Invested
AL21: {=TRANSPOSE('Assumptions Sheet'!AA13:AE13)} -> Large Cap | AM21: ='Optimizer Engine'!F1 -> 0.1 | AN21: =IF(SUM(AM21:AM25)=1, "CORRECT VALUES","INCORRECT VALUES") -> CORRECT VALUES
AL22: Mid Cap | AM22: ='Optimizer Engine'!F2 -> 0.1
AL23: Small Cap | AM23: =1-SUM(AM21:AM22) -> 0.8
AL24: FD
AG25: Annual Increment | AH25: =[1]Details!H11 -> 0.1 | AL25: Savings Account
C28: Age | E28: {=TRANSPOSE([1]Details!$B$14:$B$18)} -> Salary | F28: Rent | G28: Interest | H28: Business Income | I28: Other Income | N28: Total | Q28: {=TRANSPOSE([1]Details!$F$14:$F$22)} -> EMI | R28: Entertainment | S28: Food | T28: Recreation | U28: Medical expenses | V28: Luxury | W28: Transportation | X28: Household Expenses | Y28: Insurance | Z28: Ad Hoc | AA28: Total Expenses | AC28: Total Income | AD28: Total Expenses | AE28: Balance | AF28: Action | AG28: Investment | AH28: Cashflow to Savings A/C | AJ28: Age | AK28: Investible Amt | AL28: Invested Corpus (prv year market value + new investment | AN28: Large Cap | AS28: Mid Cap | AX28: Small Cap | BF28: Savings Account | BK28: Fixed Deposit
E29: {=TRANSPOSE([1]Details!$C$14:$C$18)} -> 720000 | F29: 0 | G29: 6000 | H29: 0 | I29: - | N29: =SUM(E29:M29) -> 726000 | Q29: {=TRANSPOSE([1]Details!$G$14:$G$22)} -> 0 | R29: 18000 | S29: 36000 | T29: 12000 | U29: 6000 | V29: 24000 | W29: 18000 | X29: 84000 | Y29: 12000 | Z29: ='Assumptions Sheet'!V21 -> 30000 | AA29: =SUM(Q29:Z29) -> 240000 | AC29: =N29 -> 726000 | AD29: =AA29 -> 240000 | AE29: =AC29-AD29 -> 486000 | AG29: =[1]Details!G10 -> 40000 | AH29: =MAX(AE29-AG29,AE29) -> 486000 | BH29: =[1]Details!V20 -> 80000
C30: Age | N30: =SUM(E30:M30) -> 0 | AK30: Investible Amt | AL30: Invested Corpus (prv year market value + new investment | AN30: Addition | AO30: End Of Year Value | AP30: Withdrawal | AQ30: Corpus | AS30: Addition | AT30: End Of Year Value | AU30: Withdrwal | AV30: Corpus | AX30: Addition | AY30: End Of Year Value | AZ30: Withdrwal | BA30: Corpus | BC30: Yearly Investment | BD30: Total Invested | BF30: Addition | BG30: Withdrwal | BH30: Corpus | BI30: Transfer to FD | BK30: Addition | BL30: Year end Value | BM30: Withdrwal | BN30: Corpus
B31: {=_xlfn.SEQUENCE([1]Details!C4-[1]Details!C3,1,[1]Details!C3,1)} -> 20 | C31: =B31 -> 20 | E31: =E29 -> 720000 | F31: =F29 -> 0 | G31: =G29 -> 6000 | H31: =H29 -> 0 | I31: =I29 -> - | N31: =SUM(E31:M31) -> 726000 | Q31: =$Q$29 -> 0 | R31: =R29 -> 18000 | S31: =S29 -> 36000 | T31: =T29 -> 12000 | U31: =U29 -> 6000 | V31: =V29 -> 24000 | W31: =W29 -> 18000 | X31: =X29 -> 84000 | Y31: =Y29 -> 12000 | Z31: ='Assumptions Sheet'!V21 -> 30000 | AA31: =SUM(Q31:Z31) -> 240000 | AC31: =N31 -> 726000 | AD31: =AA31 -> 240000 | AE31: =AC31-AD31 -> 486000 | AG31: {=_xlfn.IFS(AE31<AG29,0,AE31>AG29,AG29)} -> 40000 | AH31: =AE31-AG31 -> 446000 | AJ31: ='Calc Engine'!$C31 -> 20 | AK31: =AG31 -> 40000 | AL31: =SUM(AK31) -> 40000 | AN31: =AL31*$AM$21 -> 4000 | AO31: =(AN31*(1+'Assumptions Sheet'!AA21)) -> 4360 | AP31: =_xlfn.XLOOKUP(AJ31,[1]Details!$L$14:$L$23,[1]Details!$M$14:$M$23,0,0,1) -> 0 | AQ31: =AO31-AP31 -> 4360 | AS31: =AL31*$AM$22 -> 4000 | AT31: =AS31*(1+'Assumptions Sheet'!AB21) -> 4480 | AU31: =_xlfn.XLOOKUP(AJ31,[1]Details!$L$14:$L$23,[1]Details!$N$14:$N$23,0,0,1) -> 0 | AV31: =AT31-AU31 -> 4480 | AX31: =AK31*$AM$23 -> 32000 | AY31: =AX31*(1+'Assumptions Sheet'!AC21) -> 36480 | AZ31: =_xlfn.XLOOKUP(AJ31,[1]Details!$L$14:$L$23,[1]Details!$O$14:$O$23,0,0,1) -> 0 | BA31: =AY31-AZ31 -> 36480 | BC31: =SUM(AX31,AS31,AN31) -> 40000 | BD31: =BC31 -> 40000 | BF31: =IF(AH31>0,AH31,0) -> 446000 | BG31: =IF(AH31<0,AH31,0) -> 0 | BH31: =(BF31*(1+'Assumptions Sheet'!AE21))+BG31+Opening_Savings -> 539380 | BI31: =(IF(BH31>SUM([1]Details!$V$18,[1]Details!$V$19),[1]Details!$V$19,0)) -> 300000 | BK31: =(IF(BH31>SUM([1]Details!V18+[1]Details!V19),[1]Details!V19,0)) -> 300000 | BL31: =BK31*(1+'Assumptions Sheet'!AD21) -> 315000 | BN31: =BL31-BM31 -> 315000
B32: 21 | C32: =C31+1 -> 21 | E32: =E31*(1+'Assumptions Sheet'!E21) -> 748800 | F32: =F31*(1+'Assumptions Sheet'!F21) -> 0 | G32: =G31*(1+'Assumptions Sheet'!G21) -> 6300 | H32: =H31*(1+'Assumptions Sheet'!H21) -> 0 | N32: =SUM(E32:M32) -> 755100 | Q32: =$Q$29 -> 0 | R32: =R31*(1+'Assumptions Sheet'!Q21) -> 19800 | S32: =S31*(1+'Assumptions Sheet'!P21) -> 38520 | T32: =T31*('Assumptions Sheet'!Q21+1) -> 13200 | U32: =U31*('Assumptions Sheet'!S21+1) -> 6240 | V32: =V31*(1+'Assumptions Sheet'!Q21) -> 26400 | W32: =W31*(1+'Assumptions Sheet'!R21) -> 19080 | X32: =X31*(1+'Assumptions Sheet'!O21) -> 90720 | Y32: =Y31 -> 12000 | Z32: ='Assumptions Sheet'!V22 -> 10000 | AA32: =SUM(Q32:Z32) -> 235960 | AC32: =N32 -> 755100 | AD32: =AA32 -> 235960 | AE32: =AC32-AD32 -> 519140 | AF32: {=_xlfn.IFS(AE32<0,"Withdrawal From Savings A/C",AND(AE32>0,BH31<[1]Details!$V$18),"Transfer to Emergency Fund",AE32>$AG$29,"Investment Possible",AND(AE32>0,BH31>[1]Details!$V$18),"Investment Possible With Bal")} -> Investment Possible | AG32: {=_xlfn.IFS(OR(AF32="Withdrawal From Savings A/C",AF32="Transfer to Emergency Fund"),0,AF32= "Investment Possible With Bal",AE32,AF32= "Investment Possible",MAX($AG$29,$AG31*(1+$AH$25)))} -> 44000 | AH32: =AE32-AG32 -> 475140 | AJ32: ='Calc Engine'!$C32 -> 21 | AK32: =AG32 -> 44000 | AL32: =SUM(AK32,AL31) -> 84000 | AN32: =AK32*$AM$21 -> 4400 | AO32: =(AN32+AQ31)*(1+'Assumptions Sheet'!AA22) -> 9986.4 | AP32: =_xlfn.XLOOKUP(AJ32,[1]Details!$L$14:$L$23,[1]Details!$M$14:$M$23,0,0,1) -> 0 | AQ32: =AO32-AP32 -> 9986.4 | AS32: =AK32*$AM$22 -> 4400 | AT32: =(AV31+AS32)*(1+'Assumptions Sheet'!AB22) -> 10300.8 | AU32: =_xlfn.XLOOKUP(AJ32,[1]Details!$L$14:$L$23,[1]Details!$N$14:$N$23,0,0,1) -> 0 | AV32: =AT32-AU32 -> 10300.8 | AX32: =AK32*$AM$23 -> 35200 | AY32: =(AX32+BA31)*(1+'Assumptions Sheet'!AC22) -> 86016 | AZ32: =_xlfn.XLOOKUP(AJ32,[1]Details!$L$14:$L$23,[1]Details!$O$14:$O$23,0,0,1) -> 0 | BA32: =AY32-AZ32 -> 86016 | BC32: =SUM(AX32,AS32,AN32) -> 44000 | BD32: =BC32+BC31 -> 84000 | BF32: =IF(AH32>0,AH32,0) -> 475140 | BG32: =IF(AH32<0,AH32,0) -> 0 | BH32: =(((BF32+BH31)*(1+'Assumptions Sheet'!AE22)))-BI31+BG32 -> 744955.6 | BI32: =(IF(BH32>SUM([1]Details!$V$18,[1]Details!$V$19),[1]Details!$V$19,0)) -> 300000 | BK32: =(IF(BH32>SUM([1]Details!V19+[1]Details!V20),[1]Details!V20,0)) -> 80000 | BL32: =BK32*(1+'Assumptions Sheet'!AD22) -> 84000 | BN32: =BL32-BM32+BN31 -> 399000
B33: 22 | C33: =C32+1 -> 22 | E33: =E32*(1+'Assumptions Sheet'!E22) -> 823680 | F33: =F32*(1+'Assumptions Sheet'!F22) -> 0 | G33: =G32*(1+'Assumptions Sheet'!G22) -> 6615 | H33: =H32*(1+'Assumptions Sheet'!H22) -> 0 | N33: =SUM(E33:M33) -> 830295 | Q33: =$Q$29 -> 0 | R33: =R32*(1+'Assumptions Sheet'!Q22) -> 21384 | S33: =S32*(1+'Assumptions Sheet'!P22) -> 40060.8 | T33: =T32*('Assumptions Sheet'!Q22+1) -> 14256 | U33: =U32*('Assumptions Sheet'!S22+1) -> 6489.6 | V33: =V32*(1+'Assumptions Sheet'!Q22) -> 28512 | W33: =W32*(1+'Assumptions Sheet'!R22) -> 20224.8 | X33: =X32*(1+'Assumptions Sheet'!O22) -> 95256 | Y33: =Y32 -> 12000 | Z33: ='Assumptions Sheet'!V23 -> 15000 | AA33: =SUM(Q33:Z33) -> 253183.2 | AC33: =N33 -> 830295 | AD33: =AA33 -> 253183.2 | AE33: =AC33-AD33 -> 577111.8 | AF33: {=_xlfn.IFS(AE33<0,"Withdrawal From Savings A/C",AND(AE33>0,BH32<[1]Details!$V$18),"Transfer to Emergency Fund",AE33>$AG$29,"Investment Possible",AND(AE33>0,BH32>[1]Details!$V$18),"Investment Possible With Bal")} -> Investment Possible | AG33: {=_xlfn.IFS(OR(AF33="Withdrawal From Savings A/C",AF33="Transfer to Emergency Fund"),0,AF33= "Investment Possible With Bal",AE33,AF33= "Investment Possible",MAX($AG$29,$AG32*(1+$AH$25)))} -> 48400 | AH33: =AE33-AG33 -> 528711.8 | AJ33: ='Calc Engine'!$C33 -> 22 | AK33: =AG33 -> 48400 | AL33: =SUM(AK33,AL32) -> 132400 | AN33: =AK33*$AM$21 -> 4840 | AO33: =(AN33+AQ32)*(1+'Assumptions Sheet'!AA23) -> 16605.568 | AP33: =_xlfn.XLOOKUP(AJ33,[1]Details!$L$14:$L$23,[1]Details!$M$14:$M$23,0,0,1) -> 0 | AQ33: =AO33-AP33 -> 16605.568 | AS33: =AK33*$AM$22 -> 4840 | AT33: =(AV32+AS33)*(1+'Assumptions Sheet'!AB23) -> 17260.512 | AU33: =_xlfn.XLOOKUP(AJ33,[1]Details!$L$14:$L$23,[1]Details!$N$14:$N$23,0,0,1) -> 0 | AV33: =AT33-AU33 -> 17260.512 | AX33: =AK33*$AM$23 -> 38720 | AY33: =(AX33+BA32)*(1+'Assumptions Sheet'!AC23) -> 144693.76 | AZ33: =_xlfn.XLOOKUP(AJ33,[1]Details!$L$14:$L$23,[1]Details!$O$14:$O$23,0,0,1) -> 0 | BA33: =AY33-AZ33 -> 144693.76 | BC33: =SUM(AX33,AS33,AN33) -> 48400 | BD33: =BC33+BC32 -> 92400 | BF33: =IF(AH33>0,AH33,0) -> 528711.8 | BG33: =IF(AH33<0,AH33,0) -> 0 | BH33: =(((BF33+BH32)*(1+'Assumptions Sheet'!AE23)))-BI32+BG33 -> 1011877.4 | BI33: =(IF(BH33>SUM([1]Details!$V$18,[1]Details!$V$19),[1]Details!$V$19,0)) -> 300000 | BK33: =BI33 -> 300000 | BL33: =BK33*(1+'Assumptions Sheet'!AD23) -> 315000 | BN33: =BL33-BM33+BN32 -> 714000
B34: 23 | C34: =C33+1 -> 23 | E34: =E33*(1+'Assumptions Sheet'!E23) -> 881337.6 | F34: =F33*(1+'Assumptions Sheet'!F23) -> 0 | G34: =G33*(1+'Assumptions Sheet'!G23) -> 6945.75 | H34: =H33*(1+'Assumptions Sheet'!H23) -> 0 | N34: =SUM(E34:M34) -> 888283.35 | Q34: =$Q$29 -> 0 | R34: =R33*(1+'Assumptions Sheet'!Q23) -> 22453.2 | S34: =S33*(1+'Assumptions Sheet'!P23) -> 42063.84 | T34: =T33*('Assumptions Sheet'!Q23+1) -> 14968.8 | U34: =U33*('Assumptions Sheet'!S23+1) -> 6749.184 | V34: =V33*(1+'Assumptions Sheet'!Q23) -> 29937.6 | W34: =W33*(1+'Assumptions Sheet'!R23) -> 21438.288 | X34: =X33*(1+'Assumptions Sheet'!O23) -> 100971.36 | Y34: =Y33 -> 12000 | Z34: ='Assumptions Sheet'!V24 -> 10000 | AA34: =SUM(Q34:Z34) -> 260582.27 | AC34: =N34 -> 888283.35 | AD34: =AA34 -> 260582.27 | AE34: =AC34-AD34 -> 627701.08 | AF34: {=_xlfn.IFS(AE34<0,"Withdrawal From Savings A/C",AND(AE34>0,BH33<[1]Details!$V$18),"Transfer to Emergency Fund",AE34>$AG$29,"Investment Possible",AND(AE34>0,BH33>[1]Details!$V$18),"Investment Possible With Bal")} -> Investment Possible | AG34: {=_xlfn.IFS(OR(AF34="Withdrawal From Savings A/C",AF34="Transfer to Emergency Fund"),0,AF34= "Investment Possible With Bal",AE34,AF34= "Investment Possible",MAX($AG$29,$AG33*(1+$AH$25)))} -> 53240 | AH34: =AE34-AG34 -> 574461.08 | AJ34: ='Calc Engine'!$C34 -> 23 | AK34: =AG34 -> 53240 | AL34: =SUM(AK34,AL33) -> 185640 | AN34: =AK34*$AM$21 -> 5324 | AO34: =(AN34+AQ33)*(1+'Assumptions Sheet'!AA24) -> 24999.708 | AP34: =_xlfn.XLOOKUP(AJ34,[1]Details!$L$14:$L$23,[1]Details!$M$14:$M$23,0,0,1) -> 0 | AQ34: =AO34-AP34 -> 24999.708 | AS34: =AK34*$AM$22 -> 5324 | AT34: =(AV33+AS34)*(1+'Assumptions Sheet'!AB24) -> 26198.034 | AU34: =_xlfn.XLOOKUP(AJ34,[1]Details!$L$14:$L$23,[1]Details!$N$14:$N$23,0,0,1) -> 0 | AV34: =AT34-AU34 -> 26198.034 | AX34: =AK34*$AM$23 -> 42592 | AY34: =(AX34+BA33)*(1+'Assumptions Sheet'!AC24) -> 224742.91 | AZ34: =_xlfn.XLOOKUP(AJ34,[1]Details!$L$14:$L$23,[1]Details!$O$14:$O$23,0,0,1) -> 0 | BA34: =AY34-AZ34 -> 224742.91 | BC34: =SUM(AX34,AS34,AN34) -> 53240 | BD34: =BC34+BC33 -> 101640 | BF34: =IF(AH34>0,AH34,0) -> 574461.08 | BG34: =IF(AH34<0,AH34,0) -> 0 | BH34: =(((BF34+BH33)*(1+'Assumptions Sheet'!AE24)))-BI33+BG34 -> 1333928.7 | BI34: =(IF(BH34>SUM([1]Details!$V$18,[1]Details!$V$19),[1]Details!$V$19,0)) -> 300000 | BK34: =BI34 -> 300000 | BL34: =BK34*(1+'Assumptions Sheet'!AD24) -> 315000 | BN34: =BL34-BM34+BN33 -> 1029000
B35: 24 | C35: =C34+1 -> 24 | E35: =E34*(1+'Assumptions Sheet'!E24) -> 969471.36 | F35: =F34*(1+'Assumptions Sheet'!F24) -> 0 | G35: =G34*(1+'Assumptions Sheet'!G24) -> 7293.0375 | H35: =H34*(1+'Assumptions Sheet'!H24) -> 0 | N35: =SUM(E35:M35) -> 976764.4 | Q35: =$Q$29 -> 0 | R35: =R34*(1+'Assumptions Sheet'!Q24) -> 24249.456 | S35: =S34*(1+'Assumptions Sheet'!P24) -> 43746.394 | T35: =T34*('Assumptions Sheet'!Q24+1) -> 16166.304 | U35: =U34*('Assumptions Sheet'!S24+1) -> 7019.1514 | V35: =V34*(1+'Assumptions Sheet'!Q24) -> 32332.608 | W35: =W34*(1+'Assumptions Sheet'!R24) -> 22724.585 | X35: =X34*(1+'Assumptions Sheet'!O24) -> 106019.93 | Y35: =Y34 -> 12000 | Z35: ='Assumptions Sheet'!V25 -> 10000 | AA35: =SUM(Q35:Z35) -> 274258.43 | AC35: =N35 -> 976764.4 | AD35: =AA35 -> 274258.43 | AE35: =AC35-AD35 -> 702505.97 | AF35: {=_xlfn.IFS(AE35<0,"Withdrawal From Savings A/C",AND(AE35>0,BH34<[1]Details!$V$18),"Transfer to Emergency Fund",AE35>$AG$29,"Investment Possible",AND(AE35>0,BH34>[1]Details!$V$18),"Investment Possible With Bal")} -> Investment Possible | AG35: {=_xlfn.IFS(OR(AF35="Withdrawal From Savings A/C",AF35="Transfer to Emergency Fund"),0,AF35= "Investment Possible With Bal",AE35,AF35= "Investment Possible",MAX($AG$29,$AG34*(1+$AH$25)))} -> 58564 | AH35: =AE35-AG35 -> 643941.97 | AJ35: ='Calc Engine'!$C35 -> 24 | AK35: =AG35 -> 58564 | AL35: =SUM(AK35,AL34) -> 244204 | AN35: =AK35*$AM$21 -> 5856.4 | AO35: =(AN35+AQ34)*(1+'Assumptions Sheet'!AA25) -> 35175.963 | AP35: =_xlfn.XLOOKUP(AJ35,[1]Details!$L$14:$L$23,[1]Details!$M$14:$M$23,0,0,1) -> 0 | AQ35: =AO35-AP35 -> 35175.963 | AS35: =AK35*$AM$22 -> 5856.4 | AT35: =(AV34+AS35)*(1+'Assumptions Sheet'!AB25) -> 37183.143 | AU35: =_xlfn.XLOOKUP(AJ35,[1]Details!$L$14:$L$23,[1]Details!$N$14:$N$23,0,0,1) -> 0 | AV35: =AT35-AU35 -> 37183.143 | AX35: =AK35*$AM$23 -> 46851.2 | AY35: =(AX35+BA34)*(1+'Assumptions Sheet'!AC25) -> 325912.93 | AZ35: =_xlfn.XLOOKUP(AJ35,[1]Details!$L$14:$L$23,[1]Details!$O$14:$O$23,0,0,1) -> 0 | BA35: =AY35-AZ35 -> 325912.93 | BC35: =SUM(AX35,AS35,AN35) -> 58564 | BD35: =BC35+BC34 -> 111804 | BF35: =IF(AH35>0,AH35,0) -> 643941.97 | BG35: =IF(AH35<0,AH35,0) -> 0 | BH35: =(((BF35+BH34)*(1+'Assumptions Sheet'!AE25)))-BI34+BG35 -> 1737206.7 | BI35: =(IF(BH35>SUM([1]Details!$V$18,[1]Details!$V$19),[1]Details!$V$19,0)) -> 300000 | BK35: =BI35 -> 300000 | BL35: =BK35*(1+'Assumptions Sheet'!AD25) -> 315000 | BN35: =BL35-BM35+BN34 -> 1344000
B36: 25 | C36: =C35+1 -> 25 | E36: =E35*(1+'Assumptions Sheet'!E25) -> 1066418.5 | F36: =F35*(1+'Assumptions Sheet'!F25) -> 0 | G36: =G35*(1+'Assumptions Sheet'!G25) -> 7657.6894 | H36: =H35*(1+'Assumptions Sheet'!H25) -> 0 | N36: =SUM(E36:M36) -> 1074076.2 | Q36: =$Q$29 -> 0 | R36: =R35*(1+'Assumptions Sheet'!Q25) -> 26189.412 | S36: =S35*(1+'Assumptions Sheet'!P25) -> 45496.249 | T36: =T35*('Assumptions Sheet'!Q25+1) -> 17459.608 | U36: =U35*('Assumptions Sheet'!S25+1) -> 7299.9174 | V36: =V35*(1+'Assumptions Sheet'!Q25) -> 34919.217 | W36: =W35*(1+'Assumptions Sheet'!R25) -> 24088.06 | X36: =X35*(1+'Assumptions Sheet'!O25) -> 111320.92 | Y36: =Y35 -> 12000 | Z36: ='Assumptions Sheet'!V26 -> 30000 | AA36: =SUM(Q36:Z36) -> 308773.39 | AC36: =N36 -> 1074076.2 | AD36: =AA36 -> 308773.39 | AE36: =AC36-AD36 -> 765302.8 | AF36: {=_xlfn.IFS(AE36<0,"Withdrawal From Savings A/C",AND(AE36>0,BH35<[1]Details!$V$18),"Transfer to Emergency Fund",AE36>$AG$29,"Investment Possible",AND(AE36>0,BH35>[1]Details!$V$18),"Investment Possible With Bal")} -> Investment Possible | AG36: {=_xlfn.IFS(OR(AF36="Withdrawal From Savings A/C",AF36="Transfer to Emergency Fund"),0,AF36= "Investment Possible With Bal",AE36,AF36= "Investment Possible",MAX($AG$29,$AG35*(1+$AH$25)))} -> 64420.4 | AH36: =AE36-AG36 -> 700882.4 | AJ36: ='Calc Engine'!$C36 -> 25 | AK36: =AG36 -> 64420.4 | AL36: =SUM(AK36,AL35) -> 308624.4 | AN36: =AK36*$AM$21 -> 6442.04 | AO36: =(AN36+AQ35)*(1+'Assumptions Sheet'!AA26) -> 45363.623 | AP36: =_xlfn.XLOOKUP(AJ36,[1]Details!$L$14:$L$23,[1]Details!$M$14:$M$23,0,0,1) -> 0 | AQ36: =AO36-AP36 -> 45363.623 | AS36: =AK36*$AM$22 -> 6442.04 | AT36: =(AV35+AS36)*(1+'Assumptions Sheet'!AB26) -> 48860.205 | AU36: =_xlfn.XLOOKUP(AJ36,[1]Details!$L$14:$L$23,[1]Details!$N$14:$N$23,0,0,1) -> 0 | AV36: =AT36-AU36 -> 48860.205 | AX36: =AK36*$AM$23 -> 51536.32 | AY36: =(AX36+BA35)*(1+'Assumptions Sheet'!AC26) -> 430292.15 | AZ36: =_xlfn.XLOOKUP(AJ36,[1]Details!$L$14:$L$23,[1]Details!$O$14:$O$23,0,0,1) -> 0 | BA36: =AY36-AZ36 -> 430292.15 | BC36: =SUM(AX36,AS36,AN36) -> 64420.4 | BD36: =BC36+BC35 -> 122984.4 | BF36: =IF(AH36>0,AH36,0) -> 700882.4 | BG36: =IF(AH36<0,AH36,0) -> 0 | BH36: =(((BF36+BH35)*(1+'Assumptions Sheet'!AE26)))-BI35+BG36 -> 2211231.8 | BI36: =(IF(BH36>SUM([1]Details!$V$18,[1]Details!$V$19),[1]Details!$V$19,0)) -> 300000 | BK36: =BI36 -> 300000 | BL36: =BK36*(1+'Assumptions Sheet'!AD26) -> 315000 | BN36: =BL36-BM36+BN35 -> 1659000
B37: 26 | C37: =C36+1 -> 26 | E37: =E36*(1+'Assumptions Sheet'!E26) -> 1109075.2 | F37: =F36*(1+'Assumptions Sheet'!F26) -> 0 | G37: =G36*(1+'Assumptions Sheet'!G26) -> 8040.5738 | H37: =H36*(1+'Assumptions Sheet'!H26) -> 0 | N37: =SUM(E37:M37) -> 1117115.8 | Q37: =$Q$29 -> 0 | R37: =R36*(1+'Assumptions Sheet'!Q26) -> 28808.354 | S37: =S36*(1+'Assumptions Sheet'!P26) -> 48680.987 | T37: =T36*('Assumptions Sheet'!Q26+1) -> 19205.569 | U37: =U36*('Assumptions Sheet'!S26+1) -> 7591.9141 | V37: =V36*(1+'Assumptions Sheet'!Q26) -> 38411.138 | W37: =W36*(1+'Assumptions Sheet'!R26) -> 25533.344 | X37: =X36*(1+'Assumptions Sheet'!O26) -> 120226.6 | Y37: =Y36 -> 12000 | Z37: ='Assumptions Sheet'!V27 -> 10000 | AA37: =SUM(Q37:Z37) -> 310457.9 | AC37: =N37 -> 1117115.8 | AD37: =AA37 -> 310457.9 | AE37: =AC37-AD37 -> 806657.91 | AF37: {=_xlfn.IFS(AE37<0,"Withdrawal From Savings A/C",AND(AE37>0,BH36<[1]Details!$V$18),"Transfer to Emergency Fund",AE37>$AG$29,"Investment Possible",AND(AE37>0,BH36>[1]Details!$V$18),"Investment Possible With Bal")} -> Investment Possible | AG37: {=_xlfn.IFS(OR(AF37="Withdrawal From Savings A/C",AF37="Transfer to Emergency Fund"),0,AF37= "Investment Possible With Bal",AE37,AF37= "Investment Possible",MAX($AG$29,$AG36*(1+$AH$25)))} -> 70862.44 | AH37: =AE37-AG37 -> 735795.47 | AJ37: ='Calc Engine'!$C37 -> 26 | AK37: =AG37 -> 70862.44 | AL37: =SUM(AK37,AL36) -> 379486.84 | AN37: =AK37*$AM$21 -> 7086.244 | AO37: =(AN37+AQ36)*(1+'Assumptions Sheet'!AA27) -> 59792.848 | AP37: =_xlfn.XLOOKUP(AJ37,[1]Details!$L$14:$L$23,[1]Details!$M$14:$M$23,0,0,1) -> 0 | AQ37: =AO37-AP37 -> 59792.848 | AS37: =AK37*$AM$22 -> 7086.244 | AT37: =(AV36+AS37)*(1+'Assumptions Sheet'!AB27) -> 64897.881 | AU37: =_xlfn.XLOOKUP(AJ37,[1]Details!$L$14:$L$23,[1]Details!$N$14:$N$23,0,0,1) -> 0 | AV37: =AT37-AU37 -> 64897.881 | AX37: =AK37*$AM$23 -> 56689.952 | AY37: =(AX37+BA36)*(1+'Assumptions Sheet'!AC27) -> 584378.52 | AZ37: =_xlfn.XLOOKUP(AJ37,[1]Details!$L$14:$L$23,[1]Details!$O$14:$O$23,0,0,1) -> 0 | BA37: =AY37-AZ37 -> 584378.52 | BC37: =SUM(AX37,AS37,AN37) -> 70862.44 | BD37: =BC37+BC36 -> 135282.84 | BF37: =IF(AH37>0,AH37,0) -> 735795.47 | BG37: =IF(AH37<0,AH37,0) -> 0 | BH37: =(((BF37+BH36)*(1+'Assumptions Sheet'!AE27)))-BI36+BG37 -> 2735438.1 | BI37: =(IF(BH37>SUM([1]Details!$V$18,[1]Details!$V$19),[1]Details!$V$19,0)) -> 300000 | BK37: =BI37 -> 300000 | BL37: =BK37*(1+'Assumptions Sheet'!AD27) -> 315000 | BN37: =BL37-BM37+BN36 -> 1974000
B38: 27 | C38: =C37+1 -> 27 | E38: =E37*(1+'Assumptions Sheet'!E27) -> 1219982.8 | F38: =F37*(1+'Assumptions Sheet'!F27) -> 0 | G38: =G37*(1+'Assumptions Sheet'!G27) -> 8442.6025 | H38: =H37*(1+'Assumptions Sheet'!H27) -> 0 | N38: =SUM(E38:M38) -> 1228425.4 | Q38: =$Q$29 -> 0 | R38: =R37*(1+'Assumptions Sheet'!Q27) -> 31113.022 | S38: =S37*(1+'Assumptions Sheet'!P27) -> 50628.226 | T38: =T37*('Assumptions Sheet'!Q27+1) -> 20742.015 | U38: =U37*('Assumptions Sheet'!S27+1) -> 7895.5907 | V38: =V37*(1+'Assumptions Sheet'!Q27) -> 41484.029 | W38: =W37*(1+'Assumptions Sheet'!R27) -> 27065.345 | X38: =X37*(1+'Assumptions Sheet'!O27) -> 126237.93 | Y38: =Y37 -> 12000 | Z38: ='Assumptions Sheet'!V28 -> 10000 | AA38: =SUM(Q38:Z38) -> 327166.16 | AC38: =N38 -> 1228425.4 | AD38: =AA38 -> 327166.16 | AE38: =AC38-AD38 -> 901259.21 | AF38: {=_xlfn.IFS(AE38<0,"Withdrawal From Savings A/C",AND(AE38>0,BH37<[1]Details!$V$18),"Transfer to Emergency Fund",AE38>$AG$29,"Investment Possible",AND(AE38>0,BH37>[1]Details!$V$18),"Investment Possible With Bal")} -> Investment Possible | AG38: {=_xlfn.IFS(OR(AF38="Withdrawal From Savings A/C",AF38="Transfer to Emergency Fund"),0,AF38= "Investment Possible With Bal",AE38,AF38= "Investment Possible",MAX($AG$29,$AG37*(1+$AH$25)))} -> 77948.684 | AH38: =AE38-AG38 -> 823310.52 | AJ38: ='Calc Engine'!$C38 -> 27 | AK38: =AG38 -> 77948.684 | AL38: =SUM(AK38,AL37) -> 457435.52 | AN38: =AK38*$AM$21 -> 7794.8684 | AO38: =(AN38+AQ37)*(1+'Assumptions Sheet'!AA28) -> 77049.997 | AP38: =_xlfn.XLOOKUP(AJ38,[1]Details!$L$14:$L$23,[1]Details!$M$14:$M$23,0,0,1) -> 0 | AQ38: =AO38-AP38 -> 77049.997 | AS38: =AK38*$AM$22 -> 7794.8684 | AT38: =(AV37+AS38)*(1+'Assumptions Sheet'!AB28) -> 84323.59 | AU38: =_xlfn.XLOOKUP(AJ38,[1]Details!$L$14:$L$23,[1]Details!$N$14:$N$23,0,0,1) -> 0 | AV38: =AT38-AU38 -> 84323.59 | AX38: =AK38*$AM$23 -> 62358.947 | AY38: =(AX38+BA37)*(1+'Assumptions Sheet'!AC28) -> 776084.96 | AZ38: =_xlfn.XLOOKUP(AJ38,[1]Details!$L$14:$L$23,[1]Details!$O$14:$O$23,0,0,1) -> 0 | BA38: =AY38-AZ38 -> 776084.96 | BC38: =SUM(AX38,AS38,AN38) -> 77948.684 | BD38: =BC38+BC37 -> 148811.12 | BF38: =IF(AH38>0,AH38,0) -> 823310.52 | BG38: =IF(AH38<0,AH38,0) -> 0 | BH38: =(((BF38+BH37)*(1+'Assumptions Sheet'!AE28)))-BI37+BG38 -> 3365511.1 | BI38: =(IF(BH38>SUM([1]Details!$V$18,[1]Details!$V$19),[1]Details!$V$19,0)) -> 300000 | BK38: =BI38 -> 300000 | BL38: =BK38*(1+'Assumptions Sheet'!AD28) -> 315000 | BN38: =BL38-BM38+BN37 -> 2289000
B39: 28 | C39: =C38+1 -> 28 | E39: =E38*(1+'Assumptions Sheet'!E28) -> 1341981 | F39: =F38*(1+'Assumptions Sheet'!F28) -> 0 | G39: =G38*(1+'Assumptions Sheet'!G28) -> 8864.7327 | H39: =H38*(1+'Assumptions Sheet'!H28) -> 0 | N39: =SUM(E39:M39) -> 1350845.8 | Q39: =$Q$29 -> 0 | R39: =R38*(1+'Assumptions Sheet'!Q28) -> 33602.064 | S39: =S38*(1+'Assumptions Sheet'!P28) -> 52653.355 | T39: =T38*('Assumptions Sheet'!Q28+1) -> 22401.376 | U39: =U38*('Assumptions Sheet'!S28+1) -> 8211.4143 | V39: =V38*(1+'Assumptions Sheet'!Q28) -> 44802.752 | W39: =W38*(1+'Assumptions Sheet'!R28) -> 28689.265 | X39: =X38*(1+'Assumptions Sheet'!O28) -> 132549.82 | Y39: =Y38 -> 12000 | Z39: ='Assumptions Sheet'!V29 -> 10000 | AA39: =SUM(Q39:Z39) -> 344910.05 | AC39: =N39 -> 1350845.8 | AD39: =AA39 -> 344910.05 | AE39: =AC39-AD39 -> 1005935.7 | AF39: {=_xlfn.IFS(AE39<0,"Withdrawal From Savings A/C",AND(AE39>0,BH38<[1]Details!$V$18),"Transfer to Emergency Fund",AE39>$AG$29,"Investment Possible",AND(AE39>0,BH38>[1]Details!$V$18),"Investment Possible With Bal")} -> Investment Possible | AG39: {=_xlfn.IFS(OR(AF39="Withdrawal From Savings A/C",AF39="Transfer to Emergency Fund"),0,AF39= "Investment Possible With Bal",AE39,AF39= "Investment Possible",MAX($AG$29,$AG38*(1+$AH$25)))} -> 85743.552 | AH39: =AE39-AG39 -> 920192.16 | AJ39: ='Calc Engine'!$C39 -> 28 | AK39: =AG39 -> 85743.552 | AL39: =SUM(AK39,AL38) -> 543179.08 | AN39: =AK39*$AM$21 -> 8574.3552 | AO39: =(AN39+AQ38)*(1+'Assumptions Sheet'!AA29) -> 97611.761 | AP39: =_xlfn.XLOOKUP(AJ39,[1]Details!$L$14:$L$23,[1]Details!$M$14:$M$23,0,0,1) -> 0 | AQ39: =AO39-AP39 -> 97611.761 | AS39: =AK39*$AM$22 -> 8574.3552 | AT39: =(AV38+AS39)*(1+'Assumptions Sheet'!AB29) -> 107761.62 | AU39: =_xlfn.XLOOKUP(AJ39,[1]Details!$L$14:$L$23,[1]Details!$N$14:$N$23,0,0,1) -> 209000 | AV39: =AT39-AU39 -> -101238.38 | AX39: =AK39*$AM$23 -> 68594.842 | AY39: =(AX39+BA38)*(1+'Assumptions Sheet'!AC29) -> 1013615.8 | AZ39: =_xlfn.XLOOKUP(AJ39,[1]Details!$L$14:$L$23,[1]Details!$O$14:$O$23,0,0,1) -> 0 | BA39: =AY39-AZ39 -> 1013615.8 | BC39: =SUM(AX39,AS39,AN39) -> 85743.552 | BD39: =BC39+BC38 -> 163692.24 | BF39: =IF(AH39>0,AH39,0) -> 920192.16 | BG39: =IF(AH39<0,AH39,0) -> 0 | BH39: =(((BF39+BH38)*(1+'Assumptions Sheet'!AE29)))-BI38+BG39 -> 4114274.3 | BI39: =(IF(BH39>SUM([1]Details!$V$18,[1]Details!$V$19),[1]Details!$V$19,0)) -> 300000 | BK39: =BI39 -> 300000 | BL39: =BK39*(1+'Assumptions Sheet'!AD29) -> 315000 | BN39: =BL39-BM39+BN38 -> 2604000
B40: 29 | C40: =C39+1 -> 29 | E40: =E39*(1+'Assumptions Sheet'!E29) -> 1476179.1 | F40: =F39*(1+'Assumptions Sheet'!F29) -> 0 | G40: =G39*(1+'Assumptions Sheet'!G29) -> 9307.9693 | H40: =H39*(1+'Assumptions Sheet'!H29) -> 0 | N40: =SUM(E40:M40) -> 1485487.1 | Q40: =$Q$29 -> 0 | R40: =R39*(1+'Assumptions Sheet'!Q29) -> 36290.229 | S40: =S39*(1+'Assumptions Sheet'!P29) -> 54759.49 | T40: =T39*('Assumptions Sheet'!Q29+1) -> 24193.486 | U40: =U39*('Assumptions Sheet'!S29+1) -> 8539.8709 | V40: =V39*(1+'Assumptions Sheet'!Q29) -> 48386.972 | W40: =W39*(1+'Assumptions Sheet'!R29) -> 30410.621 | X40: =X39*(1+'Assumptions Sheet'!O29) -> 139177.32 | Y40: =Y39 -> 12000 | Z40: ='Assumptions Sheet'!V30 -> 10000 | AA40: =SUM(Q40:Z40) -> 363757.98 | AC40: =N40 -> 1485487.1 | AD40: =AA40 -> 363757.98 | AE40: =AC40-AD40 -> 1121729.1 | AF40: {=_xlfn.IFS(AE40<0,"Withdrawal From Savings A/C",AND(AE40>0,BH39<[1]Details!$V$18),"Transfer to Emergency Fund",AE40>$AG$29,"Investment Possible",AND(AE40>0,BH39>[1]Details!$V$18),"Investment Possible With Bal")} -> Investment Possible | AG40: {=_xlfn.IFS(OR(AF40="Withdrawal From Savings A/C",AF40="Transfer to Emergency Fund"),0,AF40= "Investment Possible With Bal",AE40,AF40= "Investment Possible",MAX($AG$29,$AG39*(1+$AH$25)))} -> 94317.908 | AH40: =AE40-AG40 -> 1027411.2 | AJ40: ='Calc Engine'!$C40 -> 29 | AK40: =AG40 -> 94317.908 | AL40: =SUM(AK40,AL39) -> 637496.98 | AN40: =AK40*$AM$21 -> 9431.7908 | AO40: =(AN40+AQ39)*(1+'Assumptions Sheet'!AA30) -> 122029.65 | AP40: =_xlfn.XLOOKUP(AJ40,[1]Details!$L$14:$L$23,[1]Details!$M$14:$M$23,0,0,1) -> 0 | AQ40: =AO40-AP40 -> 122029.65 | AS40: =AK40*$AM$22 -> 9431.7908 | AT40: =(AV39+AS40)*(1+'Assumptions Sheet'!AB30) -> -106495.65 | AU40: =_xlfn.XLOOKUP(AJ40,[1]Details!$L$14:$L$23,[1]Details!$N$14:$N$23,0,0,1) -> 0 | AV40: =AT40-AU40 -> -106495.65 | AX40: =AK40*$AM$23 -> 75454.326 | AY40: =(AX40+BA39)*(1+'Assumptions Sheet'!AC30) -> 1306884.1 | AZ40: =_xlfn.XLOOKUP(AJ40,[1]Details!$L$14:$L$23,[1]Details!$O$14:$O$23,0,0,1) -> 0 | BA40: =AY40-AZ40 -> 1306884.1 | BC40: =SUM(AX40,AS40,AN40) -> 94317.908 | BD40: =BC40+BC39 -> 180061.46 | BF40: =IF(AH40>0,AH40,0) -> 1027411.2 | BG40: =IF(AH40<0,AH40,0) -> 0 | BH40: =(((BF40+BH39)*(1+'Assumptions Sheet'!AE30)))-BI39+BG40 -> 4995936.1 | BI40: =(IF(BH40>SUM([1]Details!$V$18,[1]Details!$V$19),[1]Details!$V$19,0)) -> 300000 | BK40: =BI40 -> 300000 | BL40: =BK40*(1+'Assumptions Sheet'!AD30) -> 315000 | BN40: =BL40-BM40+BN39 -> 2919000
B41: 30 | C41: =C40+1 -> 30 | E41: =E40*(1+'Assumptions Sheet'!E30) -> 1623797.1 | F41: =F40*(1+'Assumptions Sheet'!F30) -> 0 | G41: =G40*(1+'Assumptions Sheet'!G30) -> 9773.3678 | H41: =H40*(1+'Assumptions Sheet'!H30) -> 0 | N41: =SUM(E41:M41) -> 1633570.4 | Q41: =$Q$29 -> 0 | R41: =R40*(1+'Assumptions Sheet'!Q30) -> 39193.447 | S41: =S40*(1+'Assumptions Sheet'!P30) -> 56949.869 | T41: =T40*('Assumptions Sheet'!Q30+1) -> 26128.965 | U41: =U40*('Assumptions Sheet'!S30+1) -> 8881.4657 | V41: =V40*(1+'Assumptions Sheet'!Q30) -> 52257.93 | W41: =W40*(1+'Assumptions Sheet'!R30) -> 32235.259 | X41: =X40*(1+'Assumptions Sheet'!O30) -> 146136.18 | Y41: =Y40 -> 12000 | Z41: ='Assumptions Sheet'!V31 -> 15000 | AA41: =SUM(Q41:Z41) -> 388783.12 | AC41: =N41 -> 1633570.4 | AD41: =AA41 -> 388783.12 | AE41: =AC41-AD41 -> 1244787.3 | AF41: {=_xlfn.IFS(AE41<0,"Withdrawal From Savings A/C",AND(AE41>0,BH40<[1]Details!$V$18),"Transfer to Emergency Fund",AE41>$AG$29,"Investment Possible",AND(AE41>0,BH40>[1]Details!$V$18),"Investment Possible With Bal")} -> Investment Possible | AG41: {=_xlfn.IFS(OR(AF41="Withdrawal From Savings A/C",AF41="Transfer to Emergency Fund"),0,AF41= "Investment Possible With Bal",AE41,AF41= "Investment Possible",MAX($AG$29,$AG40*(1+$AH$25)))} -> 103749.7 | AH41: =AE41-AG41 -> 1141037.6 | AJ41: ='Calc Engine'!$C41 -> 30 | AK41: =AG41 -> 103749.7 | AL41: =SUM(AK41,AL40) -> 741246.68 | AN41: =AK41*$AM$21 -> 10374.97 | AO41: =(AN41+AQ40)*(1+'Assumptions Sheet'!AA31) -> 148293.17 | AP41: =_xlfn.XLOOKUP(AJ41,[1]Details!$L$14:$L$23,[1]Details!$M$14:$M$23,0,0,1) -> 0 | AQ41: =AO41-AP41 -> 148293.17 | AS41: =AK41*$AM$22 -> 10374.97 | AT41: =(AV40+AS41)*(1+'Assumptions Sheet'!AB31) -> -109577.57 | AU41: =_xlfn.XLOOKUP(AJ41,[1]Details!$L$14:$L$23,[1]Details!$N$14:$N$23,0,0,1) -> 0 | AV41: =AT41-AU41 -> -109577.57 | AX41: =AK41*$AM$23 -> 82999.759 | AY41: =(AX41+BA40)*(1+'Assumptions Sheet'!AC31) -> 1612265.3 | AZ41: =_xlfn.XLOOKUP(AJ41,[1]Details!$L$14:$L$23,[1]Details!$O$14:$O$23,0,0,1) -> 0 | BA41: =AY41-AZ41 -> 1612265.3 | BC41: =SUM(AX41,AS41,AN41) -> 103749.7 | BD41: =BC41+BC40 -> 198067.61 | BF41: =IF(AH41>0,AH41,0) -> 1141037.6 | BG41: =IF(AH41<0,AH41,0) -> 0 | BH41: =(((BF41+BH40)*(1+'Assumptions Sheet'!AE31)))-BI40+BG41 -> 6021082.9 | BI41: =(IF(BH41>SUM([1]Details!$V$18,[1]Details!$V$19),[1]Details!$V$19,0)) -> 300000 | BK41: =BI41 -> 300000 | BL41: =BK41*(1+'Assumptions Sheet'!AD31) -> 315000 | BN41: =BL41-BM41+BN40 -> 3234000
B42: 31 | C42: =C41+1 -> 31 | E42: =E41*(1+'Assumptions Sheet'!E31) -> 1737462.8 | F42: =F41*(1+'Assumptions Sheet'!F31) -> 0 | G42: =G41*(1+'Assumptions Sheet'!G31) -> 10262.036 | H42: =H41*(1+'Assumptions Sheet'!H31) -> 0 | N42: =SUM(E42:M42) -> 1747724.9 | Q42: =$Q$29 -> 0 | R42: =R41*(1+'Assumptions Sheet'!Q31) -> 41153.12 | S42: =S41*(1+'Assumptions Sheet'!P31) -> 59797.363 | T42: =T41*('Assumptions Sheet'!Q31+1) -> 27435.413 | U42: =U41*('Assumptions Sheet'!S31+1) -> 9236.7243 | V42: =V41*(1+'Assumptions Sheet'!Q31) -> 54870.826 | W42: =W41*(1+'Assumptions Sheet'!R31) -> 34169.374 | X42: =X41*(1+'Assumptions Sheet'!O31) -> 154904.35 | Y42: =Y41 -> 12000 | Z42: ='Assumptions Sheet'!V32 -> 10000 | AA42: =SUM(Q42:Z42) -> 403567.17 | AC42: =N42 -> 1747724.9 | AD42: =AA42 -> 403567.17 | AE42: =AC42-AD42 -> 1344157.7 | AF42: {=_xlfn.IFS(AE42<0,"Withdrawal From Savings A/C",AND(AE42>0,BH41<[1]Details!$V$18),"Transfer to Emergency Fund",AE42>$AG$29,"Investment Possible",AND(AE42>0,BH41>[1]Details!$V$18),"Investment Possible With Bal")} -> Investment Possible | AG42: {=_xlfn.IFS(OR(AF42="Withdrawal From Savings A/C",AF42="Transfer to Emergency Fund"),0,AF42= "Investment Possible With Bal",AE42,AF42= "Investment Possible",MAX($AG$29,$AG41*(1+$AH$25)))} -> 114124.67 | AH42: =AE42-AG42 -> 1230033 | AJ42: ='Calc Engine'!$C42 -> 31 | AK42: =AG42 -> 114124.67 | AL42: =SUM(AK42,AL41) -> 855371.35 | AN42: =AK42*$AM$21 -> 11412.467 | AO42: =(AN42+AQ41)*(1+'Assumptions Sheet'!AA32) -> 182064.43 | AP42: =_xlfn.XLOOKUP(AJ42,[1]Details!$L$14:$L$23,[1]Details!$M$14:$M$23,0,0,1) -> 0 | AQ42: =AO42-AP42 -> 182064.43 | AS42: =AK42*$AM$22 -> 11412.467 | AT42: =(AV41+AS42)*(1+'Assumptions Sheet'!AB32) -> -113871.52 | AU42: =_xlfn.XLOOKUP(AJ42,[1]Details!$L$14:$L$23,[1]Details!$N$14:$N$23,0,0,1) -> 0 | AV42: =AT42-AU42 -> -113871.52 | AX42: =AK42*$AM$23 -> 91299.735 | AY42: =(AX42+BA41)*(1+'Assumptions Sheet'!AC32) -> 2044278 | AZ42: =_xlfn.XLOOKUP(AJ42,[1]Details!$L$14:$L$23,[1]Details!$O$14:$O$23,0,0,1) -> 0 | BA42: =AY42-AZ42 -> 2044278 | BC42: =SUM(AX42,AS42,AN42) -> 114124.67 | BD42: =BC42+BC41 -> 217874.37 | BF42: =IF(AH42>0,AH42,0) -> 1230033 | BG42: =IF(AH42<0,AH42,0) -> 0 | BH42: =(((BF42+BH41)*(1+'Assumptions Sheet'!AE32)))-BI41+BG42 -> 7168649.5 | BI42: =(IF(BH42>SUM([1]Details!$V$18,[1]Details!$V$19),[1]Details!$V$19,0)) -> 300000 | BK42: =BI42 -> 300000 | BL42: =BK42*(1+'Assumptions Sheet'!AD32) -> 315000 | BN42: =BL42-BM42+BN41 -> 3549000
B43: 32 | C43: =C42+1 -> 32 | E43: =E42*(1+'Assumptions Sheet'!E32) -> 1911209.1 | F43: =F42*(1+'Assumptions Sheet'!F32) -> 0 | G43: =G42*(1+'Assumptions Sheet'!G32) -> 10775.138 | H43: =H42*(1+'Assumptions Sheet'!H32) -> 0 | N43: =SUM(E43:M43) -> 1921984.3 | Q43: =$Q$29 -> 0 | R43: =R42*(1+'Assumptions Sheet'!Q32) -> 44445.369 | S43: =S42*(1+'Assumptions Sheet'!P32) -> 62189.257 | T43: =T42*('Assumptions Sheet'!Q32+1) -> 29630.246 | U43: =U42*('Assumptions Sheet'!S32+1) -> 9606.1933 | V43: =V42*(1+'Assumptions Sheet'!Q32) -> 59260.492 | W43: =W42*(1+'Assumptions Sheet'!R32) -> 36219.536 | X43: =X42*(1+'Assumptions Sheet'!O32) -> 162649.57 | Y43: =Y42 -> 12000 | Z43: ='Assumptions Sheet'!V33 -> 10000 | AA43: =SUM(Q43:Z43) -> 426000.66 | AC43: =N43 -> 1921984.3 | AD43: =AA43 -> 426000.66 | AE43: =AC43-AD43 -> 1495983.6 | AF43: {=_xlfn.IFS(AE43<0,"Withdrawal From Savings A/C",AND(AE43>0,BH42<[1]Details!$V$18),"Transfer to Emergency Fund",AE43>$AG$29,"Investment Possible",AND(AE43>0,BH42>[1]Details!$V$18),"Investment Possible With Bal")} -> Investment Possible | AG43: {=_xlfn.IFS(OR(AF43="Withdrawal From Savings A/C",AF43="Transfer to Emergency Fund"),0,AF43= "Investment Possible With Bal",AE43,AF43= "Investment Possible",MAX($AG$29,$AG42*(1+$AH$25)))} -> 125537.14 | AH43: =AE43-AG43 -> 1370446.5 | AJ43: ='Calc Engine'!$C43 -> 32 | AK43: =AG43 -> 125537.14 | AL43: =SUM(AK43,AL42) -> 980908.49 | AN43: =AK43*$AM$21 -> 12553.714 | AO43: =(AN43+AQ42)*(1+'Assumptions Sheet'!AA33) -> 221864.68 | AP43: =_xlfn.XLOOKUP(AJ43,[1]Details!$L$14:$L$23,[1]Details!$M$14:$M$23,0,0,1) -> 660000 | AQ43: =AO43-AP43 -> -438135.32 | AS43: =AK43*$AM$22 -> 12553.714 | AT43: =(AV42+AS43)*(1+'Assumptions Sheet'!AB33) -> -117528.66 | AU43: =_xlfn.XLOOKUP(AJ43,[1]Details!$L$14:$L$23,[1]Details!$N$14:$N$23,0,0,1) -> 0 | AV43: =AT43-AU43 -> -117528.66 | AX43: =AK43*$AM$23 -> 100429.71 | AY43: =(AX43+BA42)*(1+'Assumptions Sheet'!AC33) -> 2573649.3 | AZ43: =_xlfn.XLOOKUP(AJ43,[1]Details!$L$14:$L$23,[1]Details!$O$14:$O$23,0,0,1) -> 0 | BA43: =AY43-AZ43 -> 2573649.3 | BC43: =SUM(AX43,AS43,AN43) -> 125537.14 | BD43: =BC43+BC42 -> 239661.8 | BF43: =IF(AH43>0,AH43,0) -> 1370446.5 | BG43: =IF(AH43<0,AH43,0) -> 0 | BH43: =(((BF43+BH42)*(1+'Assumptions Sheet'!AE33)))-BI42+BG43 -> 8495268.8 | BI43: =(IF(BH43>SUM([1]Details!$V$18,[1]Details!$V$19),[1]Details!$V$19,0)) -> 300000 | BK43: =BI43 -> 300000 | BL43: =BK43*(1+'Assumptions Sheet'!AD33) -> 315000 | BN43: =BL43-BM43+BN42 -> 3864000
B44: 33 | C44: =C43+1 -> 33 | E44: =E43*(1+'Assumptions Sheet'!E33) -> 2102330 | F44: =F43*(1+'Assumptions Sheet'!F33) -> 0 | G44: =G43*(1+'Assumptions Sheet'!G33) -> 11313.895 | H44: =H43*(1+'Assumptions Sheet'!H33) -> 0 | N44: =SUM(E44:M44) -> 2113643.9 | Q44: =$Q$29 -> 0 | R44: =R43*(1+'Assumptions Sheet'!Q33) -> 48000.999 | S44: =S43*(1+'Assumptions Sheet'!P33) -> 64676.827 | T44: =T43*('Assumptions Sheet'!Q33+1) -> 32000.666 | U44: =U43*('Assumptions Sheet'!S33+1) -> 9990.441 | V44: =V43*(1+'Assumptions Sheet'!Q33) -> 64001.332 | W44: =W43*(1+'Assumptions Sheet'!R33) -> 38392.709 | X44: =X43*(1+'Assumptions Sheet'!O33) -> 170782.05 | Y44: =Y43 -> 12000 | Z44: ='Assumptions Sheet'!V34 -> 10000 | AA44: =SUM(Q44:Z44) -> 449845.02 | AC44: =N44 -> 2113643.9 | AD44: =AA44 -> 449845.02 | AE44: =AC44-AD44 -> 1663798.9 | AF44: {=_xlfn.IFS(AE44<0,"Withdrawal From Savings A/C",AND(AE44>0,BH43<[1]Details!$V$18),"Transfer to Emergency Fund",AE44>$AG$29,"Investment Possible",AND(AE44>0,BH43>[1]Details!$V$18),"Investment Possible With Bal")} -> Investment Possible | AG44: {=_xlfn.IFS(OR(AF44="Withdrawal From Savings A/C",AF44="Transfer to Emergency Fund"),0,AF44= "Investment Possible With Bal",AE44,AF44= "Investment Possible",MAX($AG$29,$AG43*(1+$AH$25)))} -> 138090.85 | AH44: =AE44-AG44 -> 1525708.1 | AJ44: ='Calc Engine'!$C44 -> 33 | AK44: =AG44 -> 138090.85 | AL44: =SUM(AK44,AL43) -> 1118999.3 | AN44: =AK44*$AM$21 -> 13809.085 | AO44: =(AN44+AQ43)*(1+'Assumptions Sheet'!AA34) -> -483731.9 | AP44: =_xlfn.XLOOKUP(AJ44,[1]Details!$L$14:$L$23,[1]Details!$M$14:$M$23,0,0,1) -> 0 | AQ44: =AO44-AP44 -> -483731.9 | AS44: =AK44*$AM$22 -> 13809.085 | AT44: =(AV43+AS44)*(1+'Assumptions Sheet'!AB34) -> -120314.71 | AU44: =_xlfn.XLOOKUP(AJ44,[1]Details!$L$14:$L$23,[1]Details!$N$14:$N$23,0,0,1) -> 0 | AV44: =AT44-AU44 -> -120314.71 | AX44: =AK44*$AM$23 -> 110472.68 | AY44: =(AX44+BA43)*(1+'Assumptions Sheet'!AC34) -> 3220946.4 | AZ44: =_xlfn.XLOOKUP(AJ44,[1]Details!$L$14:$L$23,[1]Details!$O$14:$O$23,0,0,1) -> 0 | BA44: =AY44-AZ44 -> 3220946.4 | BC44: =SUM(AX44,AS44,AN44) -> 138090.85 | BD44: =BC44+BC43 -> 263627.98 | BF44: =IF(AH44>0,AH44,0) -> 1525708.1 | BG44: =IF(AH44<0,AH44,0) -> 0 | BH44: =(((BF44+BH43)*(1+'Assumptions Sheet'!AE34)))-BI43+BG44 -> 10021606 | BI44: =(IF(BH44>SUM([1]Details!$V$18,[1]Details!$V$19),[1]Details!$V$19,0)) -> 300000 | BK44: =BI44 -> 300000 | BL44: =BK44*(1+'Assumptions Sheet'!AD34) -> 315000 | BN44: =BL44-BM44+BN43 -> 4179000
... B65: 54 | C65: =C64+1 -> 54 | E65: =E64*(1+'Assumptions Sheet'!E54) -> 12450677 | F65: =F64*(1+'Assumptions Sheet'!F54) -> 0 | G65: =G64*(1+'Assumptions Sheet'!G54) -> 31520.088 | H65: =H64*(1+'Assumptions Sheet'!H54) -> 0 | N65: =SUM(E65:M65) -> 12482197 | Q65: =$Q$29 -> 0 | R65: =R64*(1+'Assumptions Sheet'!Q54) -> 223949.02 | S65: =S64*(1+'Assumptions Sheet'!P54) -> 162096.47 | T65: =T64*('Assumptions Sheet'!Q54+1) -> 149299.35 | U65: =U64*('Assumptions Sheet'!S54+1) -> 22765.898 | V65: =V64*(1+'Assumptions Sheet'!Q54) -> 298598.7 | W65: =W64*(1+'Assumptions Sheet'!R54) -> 130518.45 | X65: =X64*(1+'Assumptions Sheet'!O54) -> 522820.58 | Y65: =Y64 -> 12000 | Z65: ='Assumptions Sheet'!V55 -> 10000 | AA65: =SUM(Q65:Z65) -> 1532048.5 | AC65: =N65 -> 12482197 | AD65: =AA65 -> 1532048.5 | AE65: =AC65-AD65 -> 10950149 | AF65: {=_xlfn.IFS(AE65<0,"Withdrawal From Savings A/C",AND(AE65>0,BH64<[1]Details!$V$18),"Transfer to Emergency Fund",AE65>$AG$29,"Investment Possible",AND(AE65>0,BH64>[1]Details!$V$18),"Investment Possible With Bal")} -> Investment Possible | AG65: {=_xlfn.IFS(OR(AF65="Withdrawal From Savings A/C",AF65="Transfer to Emergency Fund"),0,AF65= "Investment Possible With Bal",AE65,AF65= "Investment Possible",MAX($AG$29,$AG64*(1+$AH$25)))} -> 1021906.8 | AH65: =AE65-AG65 -> 9928241.7 | AJ65: ='Calc Engine'!$C65 -> 54 | AK65: =AG65 -> 1021906.8 | AL65: =SUM(AK65,AL64) -> 10840975 | AN65: =AK65*$AM$21 -> 102190.68 | AO65: =(AN65+AQ64)*(1+'Assumptions Sheet'!AA55) -> -12846805 | AP65: =_xlfn.XLOOKUP(AJ65,[1]Details!$L$14:$L$23,[1]Details!$M$14:$M$23,0,0,1) -> 0 | AQ65: =AO65-AP65 -> -12846805 | AS65: =AK65*$AM$22 -> 102190.68 | AT65: =(AV64+AS65)*(1+'Assumptions Sheet'!AB55) -> -3353426.9 | AU65: =_xlfn.XLOOKUP(AJ65,[1]Details!$L$14:$L$23,[1]Details!$N$14:$N$23,0,0,1) -> 0 | AV65: =AT65-AU65 -> -3353426.9 | AX65: =AK65*$AM$23 -> 817525.44 | AY65: =(AX65+BA64)*(1+'Assumptions Sheet'!AC55) -> 78485193 | AZ65: =_xlfn.XLOOKUP(AJ65,[1]Details!$L$14:$L$23,[1]Details!$O$14:$O$23,0,0,1) -> 0 | BA65: =AY65-AZ65 -> 78485193 | BC65: =SUM(AX65,AS65,AN65) -> 1021906.8 | BD65: =BC65+BC64 -> 1950913 | BF65: =IF(AH65>0,AH65,0) -> 9928241.7 | BG65: =IF(AH65<0,AH65,0) -> 0 | BH65: =(((BF65+BH64)*(1+'Assumptions Sheet'!AE55)))-BI64+BG65 -> 1.3582002e+08 | BI65: =(IF(BH65>SUM([1]Details!$V$18,[1]Details!$V$19),[1]Details!$V$19,0)) -> 300000 | BK65: =BI65 -> 300000 | BL65: =BK65*(1+'Assumptions Sheet'!AD55) -> 315000 | BN65: =BL65-BM65+BN64 -> 10794000
C66: =C65+1 -> 55 | E66: =E65*(1+'Assumptions Sheet'!E55) -> 13695745 | F66: =F65*(1+'Assumptions Sheet'!F55) -> 0 | G66: =G65*(1+'Assumptions Sheet'!G55) -> 33096.092 | H66: =H65*(1+'Assumptions Sheet'!H55) -> 0 | N66: =SUM(E66:M66) -> 13728841 | Q66: =$Q$29 -> 0 | R66: =R65*(1+'Assumptions Sheet'!Q55) -> 241864.94 | S66: =S65*(1+'Assumptions Sheet'!P55) -> 168580.33 | T66: =T65*('Assumptions Sheet'!Q55+1) -> 161243.3 | U66: =U65*('Assumptions Sheet'!S55+1) -> 23676.534 | V66: =V65*(1+'Assumptions Sheet'!Q55) -> 322486.59 | W66: =W65*(1+'Assumptions Sheet'!R55) -> 138349.56 | X66: =X65*(1+'Assumptions Sheet'!O55) -> 548961.61 | Y66: =Y65 -> 12000 | Z66: ='Assumptions Sheet'!V56 -> 10000 | AA66: =SUM(Q66:Z66) -> 1627162.9 | AC66: =N66 -> 13728841 | AD66: =AA66 -> 1627162.9 | AE66: =AC66-AD66 -> 12101678 | AF66: {=_xlfn.IFS(AE66<0,"Withdrawal From Savings A/C",AND(AE66>0,BH65<[1]Details!$V$18),"Transfer to Emergency Fund",AE66>$AG$29,"Investment Possible",AND(AE66>0,BH65>[1]Details!$V$18),"Investment Possible With Bal")} -> Investment Possible | AG66: {=_xlfn.IFS(OR(AF66="Withdrawal From Savings A/C",AF66="Transfer to Emergency Fund"),0,AF66= "Investment Possible With Bal",AE66,AF66= "Investment Possible",MAX($AG$29,$AG65*(1+$AH$25)))} -> 1124097.5 | AH66: =AE66-AG66 -> 10977580 | AJ66: ='Calc Engine'!$C66 -> 55 | AK66: =AG66 -> 1124097.5 | AL66: =SUM(AK66,AL65) -> 11965072 | AN66: =AK66*$AM$21 -> 112409.75 | AO66: =(AN66+AQ65)*(1+'Assumptions Sheet'!AA56) -> -14517210 | AP66: =_xlfn.XLOOKUP(AJ66,[1]Details!$L$14:$L$23,[1]Details!$M$14:$M$23,0,0,1) -> 0 | AQ66: =AO66-AP66 -> -14517210 | AS66: =AK66*$AM$22 -> 112409.75 | AT66: =(AV65+AS66)*(1+'Assumptions Sheet'!AB56) -> -3759579.9 | AU66: =_xlfn.XLOOKUP(AJ66,[1]Details!$L$14:$L$23,[1]Details!$N$14:$N$23,0,0,1) -> 0 | AV66: =AT66-AU66 -> -3759579.9 | AX66: =AK66*$AM$23 -> 899277.98 | AY66: =(AX66+BA65)*(1+'Assumptions Sheet'!AC56) -> 95261365 | AZ66: =_xlfn.XLOOKUP(AJ66,[1]Details!$L$14:$L$23,[1]Details!$O$14:$O$23,0,0,1) -> 0 | BA66: =AY66-AZ66 -> 95261365 | BC66: =SUM(AX66,AS66,AN66) -> 1124097.5 | BD66: =BC66+BC65 -> 2146004.3 | BF66: =IF(AH66>0,AH66,0) -> 10977580 | BG66: =IF(AH66<0,AH66,0) -> 0 | BH66: =(((BF66+BH65)*(1+'Assumptions Sheet'!AE56)))-BI65+BG66 -> 1.5090152e+08 | BI66: =(IF(BH66>SUM([1]Details!$V$18,[1]Details!$V$19),[1]Details!$V$19,0)) -> 300000 | BK66: =BI66 -> 300000 | BL66: =BK66*(1+'Assumptions Sheet'!AD56) -> 315000 | BN66: =BL66-BM66+BN65 -> 11109000

Sheet Optimizer Engine
E1: Large | F1: 0.1
E2: Mid | F2: 0.1
C4: =Total_Surplus -> -9798829 | D4: {=TRANSPOSE('[2]Optimizer Engine'!O5:O12)} -> 0.1 | E4: 0.2 | F4: 0.3 | G4: 0.4 | H4: 0.5 | I4: 0.6 | J4: 0.7 | K4: 0.8 | N4: Large Cap | O4: Mid Cap | P4: Small Cap
C5: {='[2]Optimizer Engine'!N5:N12} -> 0.1 | D5: -9798829 | E5: -10355036 | F5: -10911243 | G5: -11467450 | H5: -12023657 | I5: -12579864 | J5: -13136071 | K5: -13692278 | M5: 1 | N5: 0.1 | O5: 0.1 | P5: =1-SUM(N5:O5) -> 0.8
C6: 0.2 | D6: -3692374.4 | E6: -4248581.4 | F6: -4804788.5 | G6: -5360995.5 | H6: -5917202.6 | I6: -6473409.7 | J6: -7029616.7 | K6: -7585823.8 | M6: =M5+1 -> 2 | N6: 0.2 | O6: =O5+0.1 -> 0.2 | P6: =1-SUM(N6:O6) -> 0.6
C7: 0.3 | D7: 2414080.3 | E7: 1857873.2 | F7: 1301666.2 | G7: 745459.1 | H7: 189252.04 | I7: -366955.01 | J7: -923162.07 | K7: -1479369.1 | M7: =M6+1 -> 3 | N7: 0.3 | O7: =O6+0.1 -> 0.3 | P7: =1-SUM(N7:O7) -> 0.4
C8: 0.4 | D8: 8520534.9 | E8: 7964327.9 | F8: 7408120.8 | G8: 6851913.8 | H8: 6295706.7 | I8: 5739499.6 | J8: 5183292.6 | K8: 4627085.5 | M8: =M7+1 -> 4 | N8: 0.4 | O8: =O7+0.1 -> 0.4 | P8: =1-SUM(N8:O8) -> 0.2
C9: 0.5 | D9: 14626990 | E9: 14070783 | F9: 13514575 | G9: 12958368 | H9: 12402161 | I9: 11845954 | J9: 11289747 | K9: 10733540 | M9: =M8+1 -> 5 | N9: 0.5 | O9: =O8+0.1 -> 0.5 | P9: =1-SUM(N9:O9) -> 0
C10: 0.6 | D10: 20733444 | E10: 20177237 | F10: 19621030 | G10: 19064823 | H10: 18508616 | I10: 17952409 | J10: 17396202 | K10: 16839995 | M10: =M9+1 -> 6 | N10: 0.6 | O10: =O9+0.1 -> 0.6 | P10: =1-SUM(N10:O10) -> -0.2
C11: 0.7 | D11: 26839899 | E11: 26283692 | F11: 25727485 | G11: 25171278 | H11: 24615071 | I11: 24058864 | J11: 23502657 | K11: 22946449 | M11: =M10+1 -> 7 | N11: 0.7 | O11: =O10+0.1 -> 0.7 | P11: =1-SUM(N11:O11) -> -0.4
C12: 0.8 | D12: 32946354 | E12: 32390146 | F12: 31833939 | G12: 31277732 | H12: 30721525 | I12: 30165318 | J12: 29609111 | K12: 29052904 | M12: =M11+1 -> 8 | N12: 0.8 | O12: =O11+0.1 -> 0.8 | P12: =1-SUM(N12:O12) -> -0.6
D14: {=_xlfn.ANCHORARRAY(D4)} -> 0.1 | E14: 0.2 | F14: 0.3 | G14: 0.4 | H14: 0.5 | I14: 0.6 | J14: 0.7 | K14: 0.8
C15: {=_xlfn.ANCHORARRAY(C5)} -> 0.1 | D15: =IF(D$4+$C5>0.9,"",ROUND(D5,0)) -> -9798829 | E15: =IF(E$4+$C5>0.9,"",ROUND(E5,0)) -> -10355036 | F15: =IF(F$4+$C5>0.9,"",ROUND(F5,0)) -> -10911243 | G15: =IF(G$4+$C5>0.9,"",ROUND(G5,0)) -> -11467450 | H15: =IF(H$4+$C5>0.9,"",ROUND(H5,0)) -> -12023657 | I15: =IF(I$4+$C5>0.9,"",ROUND(I5,0)) -> -12579864 | J15: =IF(J$4+$C5>0.9,"",ROUND(J5,0)) -> -13136071 | K15: =IF(K$4+$C5>0.9,"",ROUND(K5,0)) -> -13692278
C16: 0.2 | D16: =IF(D$4+$C6>0.9,"",ROUND(D6,0)) -> -3692374 | E16: =IF(E$4+$C6>0.9,"",ROUND(E6,0)) -> -4248581 | F16: =IF(F$4+$C6>0.9,"",ROUND(F6,0)) -> -4804788 | G16: =IF(G$4+$C6>0.9,"",ROUND(G6,0)) -> -5360996 | H16: =IF(H$4+$C6>0.9,"",ROUND(H6,0)) -> -5917203 | I16: =IF(I$4+$C6>0.9,"",ROUND(I6,0)) -> -6473410 | J16: =IF(J$4+$C6>0.9,"",ROUND(J6,0)) -> -7029617 | K16: =IF(K$4+$C6>0.9,"",ROUND(K6,0))
C17: 0.3 | D17: =IF(D$4+$C7>0.9,"",ROUND(D7,0)) -> 2414080 | E17: =IF(E$4+$C7>0.9,"",ROUND(E7,0)) -> 1857873 | F17: =IF(F$4+$C7>0.9,"",ROUND(F7,0)) -> 1301666 | G17: =IF(G$4+$C7>0.9,"",ROUND(G7,0)) -> 745459 | H17: =IF(H$4+$C7>0.9,"",ROUND(H7,0)) -> 189252 | I17: =IF(I$4+$C7>0.9,"",ROUND(I7,0)) -> -366955 | J17: =IF(J$4+$C7>0.9,"",ROUND(J7,0)) | K17: =IF(K$4+$C7>0.9,"",ROUND(K7,0))
C18: 0.4 | D18: =IF(D$4+$C8>0.9,"",ROUND(D8,0)) -> 8520535 | E18: =IF(E$4+$C8>0.9,"",ROUND(E8,0)) -> 7964328 | F18: =IF(F$4+$C8>0.9,"",ROUND(F8,0)) -> 7408121 | G18: =IF(G$4+$C8>0.9,"",ROUND(G8,0)) -> 6851914 | H18: =IF(H$4+$C8>0.9,"",ROUND(H8,0)) -> 6295707 | I18: =IF(I$4+$C8>0.9,"",ROUND(I8,0)) | J18: =IF(J$4+$C8>0.9,"",ROUND(J8,0)) | K18: =IF(K$4+$C8>0.9,"",ROUND(K8,0))
C19: 0.5 | D19: =IF(D$4+$C9>0.9,"",ROUND(D9,0)) -> 14626990 | E19: =IF(E$4+$C9>0.9,"",ROUND(E9,0)) -> 14070783 | F19: =IF(F$4+$C9>0.9,"",ROUND(F9,0)) -> 13514575 | G19: =IF(G$4+$C9>0.9,"",ROUND(G9,0)) -> 12958368 | H19: =IF(H$4+$C9>0.9,"",ROUND(H9,0)) | I19: =IF(I$4+$C9>0.9,"",ROUND(I9,0)) | J19: =IF(J$4+$C9>0.9,"",ROUND(J9,0)) | K19: =IF(K$4+$C9>0.9,"",ROUND(K9,0))
C20: 0.6 | D20: =IF(D$4+$C10>0.9,"",ROUND(D10,0)) -> 20733444 | E20: =IF(E$4+$C10>0.9,"",ROUND(E10,0)) -> 20177237 | F20: =IF(F$4+$C10>0.9,"",ROUND(F10,0)) -> 19621030 | G20: =IF(G$4+$C10>0.9,"",ROUND(G10,0)) | H20: =IF(H$4+$C10>0.9,"",ROUND(H10,0)) | I20: =IF(I$4+$C10>0.9,"",ROUND(I10,0)) | J20: =IF(J$4+$C10>0.9,"",ROUND(J10,0)) | K20: =IF(K$4+$C10>0.9,"",ROUND(K10,0))
C21: 0.7 | D21: =IF(D$4+$C11>0.9,"",ROUND(D11,0)) -> 26839899 | E21: =IF(E$4+$C11>0.9,"",ROUND(E11,0)) -> 26283692 | F21: =IF(F$4+$C11>0.9,"",ROUND(F11,0)) | G21: =IF(G$4+$C11>0.9,"",ROUND(G11,0)) | H21: =IF(H$4+$C11>0.9,"",ROUND(H11,0)) | I21: =IF(I$4+$C11>0.9,"",ROUND(I11,0)) | J21: =IF(J$4+$C11>0.9,"",ROUND(J11,0)) | K21: =IF(K$4+$C11>0.9,"",ROUND(K11,0))
C22: 0.8 | D22: =IF(D$4+$C12>0.9,"",ROUND(D12,0)) -> 32946354 | E22: =IF(E$4+$C12>0.9,"",ROUND(E12,0)) | F22: =IF(F$4+$C12>0.9,"",ROUND(F12,0)) | G22: =IF(G$4+$C12>0.9,"",ROUND(G12,0)) | H22: =IF(H$4+$C12>0.9,"",ROUND(H12,0)) | I22: =IF(I$4+$C12>0.9,"",ROUND(I12,0)) | J22: =IF(J$4+$C12>0.9,"",ROUND(J12,0)) | K22: =IF(K$4+$C12>0.9,"",ROUND(K12,0))
E25: =MAX(D15:K22) -> 32946354 | G25: Large Cap | H25: {=INDEX(D14:K14, SUMPRODUCT((D15:K22=E25)*COLUMN(D15:K22))-COLUMN(D15)+1)} -> 0.1
G26: Mid cap | H26: {=INDEX(C15:C22, SUMPRODUCT((D15:K22=E25)*ROW(D15:K22))-ROW(D15)+1)} -> 0.8
G27: Small Cap | H27: =1-H25-H26 -> 0.1
